{"type": "FeatureCollection", "features": [{"type": "Feature", "properties": {"ca": 359, "camera_make": "LAMAX", "camera_model": "X10 TAURUS", "captured_at": "2018-04-22T18:21:12.000Z", "key": "V67d0YUMx6hNu8ggNQXgDA", "pano": false, "user_key": "TH-2hDNemrhbn2Cc4Uc0jQ", "username": "kocsi"}, "geometry": {"type": "Point", "coordinates": [18.966303550093926, 47.54282550003802]}}, {"type": "Feature", "properties": {"ca": 359, "camera_make": "LAMAX", "camera_model": "X10 TAURUS", "captured_at": "2018-04-22T18:21:04.000Z", "key": "prhJR5jC7aGv5D6SmqOK1A", "pano": false, "user_key": "TH-2hDNemrhbn2Cc4Uc0jQ", "username": "kocsi"}, "geometry": {"type": "Point", "coordinates": [18.96631791012919, 47.54309946990958]}}, {"type": "Feature", "properties": {"ca": 359, "camera_make": "LAMAX", "camera_model": "X10 TAURUS", "captured_at": "2018-04-22T18:20:56.000Z", "key": "FhX5Hg8FzZHqn9_tCKPy2w", "pano": false, "user_key": "TH-2hDNemrhbn2Cc4Uc0jQ", "username": "kocsi"}, "geometry": {"type": "Point", "coordinates": [18.96626866005181, 47.54346818996419]}}, {"type": "Feature", "properties": {"ca": 359, "camera_make": "LAMAX", "camera_model": "X10 TAURUS", "captured_at": "2018-04-22T18:20:48.000Z", "key": "vR_dtcYDcLy_1kV_O2qXiA", "pano": false, "user_key": "TH-2hDNemrhbn2Cc4Uc0jQ", "username": "kocsi"}, "geometry": {"type": "Point", "coordinates": [18.96631945999752, 47.54386234999754]}}, {"type": "Feature", "properties": {"ca": 359, "camera_make": "LAMAX", "camera_model": "X10 TAURUS", "captured_at": "2018-04-22T18:20:40.000Z", "key": "3Rjn9sZ1kpftb4awYFvjcg", "pano": false, "user_key": "TH-2hDNemrhbn2Cc4Uc0jQ", "username": "kocsi"}, "geometry": {"type": "Point", "coordinates": [18.966347369976347, 47.54425085006034]}}, {"type": "Feature", "properties": {"ca": 359, "camera_make": "LAMAX", "camera_model": "X10 TAURUS", "captured_at": "2018-04-22T18:14:36.000Z", "key": "cWSP6kmvMlw2UKtTvrNlqg", "pano": false, "user_key": "TH-2hDNemrhbn2Cc4Uc0jQ", "username": "kocsi"}, "geometry": {"type": "Point", "coordinates": [18.966388060010786, 47.54269496004122]}}, {"type": "Feature", "properties": {"ca": 190, "camera_make": "FUJIFILM", "camera_model": "X100S", "captured_at": "2017-06-30T12:59:45.000Z", "key": "zfCygedVjrNaMnrmu1S4fg", "pano": false, "user_key": "TH-2hDNemrhbn2Cc4Uc0jQ", "username": "kocsi"}, "geometry": {"type": "Point", "coordinates": [18.96632397003748, 47.54436676994578]}}, {"type": "Feature", "properties": {"ca": 359, "camera_make": "LAMAX", "camera_model": "X10 TAURUS", "captured_at": "2017-04-16T12:47:12.000Z", "key": "QsMGGyF-0ZHiBGoAuM6Y_g", "pano": false, "user_key": "TH-2hDNemrhbn2Cc4Uc0jQ", "username": "kocsi"}, "geometry": {"type": "Point", "coordinates": [18.966395000000034, 47.54294166666665]}}, {"type": "Feature", "properties": {"ca": 359, "camera_make": "LAMAX", "camera_model": "X10 TAURUS", "captured_at": "2017-04-16T12:47:00.000Z", "key": "s3ERKw4pr3pIaDZqBvOTzQ", "pano": false, "user_key": "TH-2hDNemrhbn2Cc4Uc0jQ", "username": "kocsi"}, "geometry": {"type": "Point", "coordinates": [18.966338333333397, 47.54335500000002]}}, {"type": "Feature", "properties": {"ca": 359, "camera_make": "LAMAX", "camera_model": "X10 TAURUS", "captured_at": "2017-04-16T12:46:54.000Z", "key": "UiMGZw1DpR1mz8QDeMFmJw", "pano": false, "user_key": "TH-2hDNemrhbn2Cc4Uc0jQ", "username": "kocsi"}, "geometry": {"type": "Point", "coordinates": [18.96637499999997, 47.54366333333337]}}, {"type": "Feature", "properties": {"ca": 359, "camera_make": "LAMAX", "camera_model": "X10 TAURUS", "captured_at": "2017-04-16T12:46:48.000Z", "key": "_kNzu16u2CXjXyGD-LotFw", "pano": false, "user_key": "TH-2hDNemrhbn2Cc4Uc0jQ", "username": "kocsi"}, "geometry": {"type": "Point", "coordinates": [18.96633666666662, 47.54386499999998]}}, {"type": "Feature", "properties": {"ca": 359, "camera_make": "LAMAX", "camera_model": "X10 TAURUS", "captured_at": "2017-04-16T12:46:42.000Z", "key": "tAr08qNKi6aOJJqGNbm12A", "pano": false, "user_key": "TH-2hDNemrhbn2Cc4Uc0jQ", "username": "kocsi"}, "geometry": {"type": "Point", "coordinates": [18.966274999999996, 47.54405666666668]}}, {"type": "Feature", "properties": {"ca": 359, "camera_make": "LAMAX", "camera_model": "X10 TAURUS", "captured_at": "2017-04-16T12:46:36.000Z", "key": "OmiBn4ejj2BnYvWbmjVH5A", "pano": false, "user_key": "TH-2hDNemrhbn2Cc4Uc0jQ", "username": "kocsi"}, "geometry": {"type": "Point", "coordinates": [18.966290000000072, 47.54422999999997]}}, {"type": "Feature", "properties": {"ca": 359, "camera_make": "LAMAX", "camera_model": "X10 TAURUS", "captured_at": "2017-04-16T12:46:30.000Z", "key": "QVXkzkR5r617O1wnB3zcMQ", "pano": false, "user_key": "TH-2hDNemrhbn2Cc4Uc0jQ", "username": "kocsi"}, "geometry": {"type": "Point", "coordinates": [18.96637499999997, 47.54438166666665]}}]}