{"type": "FeatureCollection", "features": [{"type": "Feature", "properties": {"ca": 265.2203674316406, "camera_make": "SAMSUNG", "camera_model": "SM-N9005", "captured_at": "2018-05-14T12:42:07.801Z", "key": "OPj7fP3xU4jQG4gPvC4Ofw", "pano": false, "user_key": "i1FGvYWQoDeMVAlkvDwvUA", "username": "vst"}, "geometry": {"type": "Point", "coordinates": [19.061238151247608, 47.416392465451054]}}, {"type": "Feature", "properties": {"ca": 282.6600646972656, "camera_make": "SAMSUNG", "camera_model": "SM-N9005", "captured_at": "2018-05-14T12:42:06.609Z", "key": "7sAAm4zRiGogiaiN2T6GHw", "pano": false, "user_key": "i1FGvYWQoDeMVAlkvDwvUA", "username": "vst"}, "geometry": {"type": "Point", "coordinates": [19.061341514566948, 47.4163842062992]}}, {"type": "Feature", "properties": {"ca": 277.5130920410156, "camera_make": "SAMSUNG", "camera_model": "SM-N9005", "captured_at": "2018-05-14T12:42:05.461Z", "key": "QIgT3PAz2-pP8eLKSFkuWg", "pano": false, "user_key": "i1FGvYWQoDeMVAlkvDwvUA", "username": "vst"}, "geometry": {"type": "Point", "coordinates": [19.061442965276342, 47.41637375964547]}}, {"type": "Feature", "properties": {"ca": 302.0526123046875, "camera_make": "SAMSUNG", "camera_model": "SM-N9005", "captured_at": "2018-05-14T12:41:02.040Z", "key": "OGBLSpj7ZaD2UzfBpEDH0w", "pano": false, "user_key": "i1FGvYWQoDeMVAlkvDwvUA", "username": "vst"}, "geometry": {"type": "Point", "coordinates": [19.062049425891928, 47.41633058399589]}}, {"type": "Feature", "properties": {"ca": 215.3470916748047, "camera_make": "SAMSUNG", "camera_model": "SM-N9005", "captured_at": "2018-05-14T12:41:00.854Z", "key": "iDB5rGXN4oOHtp6i38uSjw", "pano": false, "user_key": "i1FGvYWQoDeMVAlkvDwvUA", "username": "vst"}, "geometry": {"type": "Point", "coordinates": [19.062085357584806, 47.416357542714536]}}, {"type": "Feature", "properties": {"ca": 224.2257080078125, "camera_make": "SAMSUNG", "camera_model": "SM-N9005", "captured_at": "2018-05-14T12:40:59.689Z", "key": "dh78QKjyn_vpIFNp-1a48A", "pano": false, "user_key": "i1FGvYWQoDeMVAlkvDwvUA", "username": "vst"}, "geometry": {"type": "Point", "coordinates": [19.06217090180462, 47.41642434766453]}}, {"type": "Feature", "properties": {"ca": 213.4762420654297, "camera_make": "SAMSUNG", "camera_model": "SM-N9005", "captured_at": "2018-05-14T12:40:58.584Z", "key": "lm3BCLNJnc7rKJM2E0XH5A", "pano": false, "user_key": "i1FGvYWQoDeMVAlkvDwvUA", "username": "vst"}, "geometry": {"type": "Point", "coordinates": [19.06223838722599, 47.41648660695898]}}, {"type": "Feature", "properties": {"ca": 220.6655731201172, "camera_make": "SAMSUNG", "camera_model": "SM-N9005", "captured_at": "2018-05-14T12:40:57.085Z", "key": "j1yyhoGRsgepBoEEwmBzcw", "pano": false, "user_key": "i1FGvYWQoDeMVAlkvDwvUA", "username": "vst"}, "geometry": {"type": "Point", "coordinates": [19.062356153846167, 47.41659172051283]}}, {"type": "Feature", "properties": {"ca": 220.7433624267578, "camera_make": "SAMSUNG", "camera_model": "SM-N9005", "captured_at": "2018-05-14T12:40:55.889Z", "key": "deczenxgceMaCq45J0cgQA", "pano": false, "user_key": "i1FGvYWQoDeMVAlkvDwvUA", "username": "vst"}, "geometry": {"type": "Point", "coordinates": [19.06246049599997, 47.41667406800002]}}, {"type": "Feature", "properties": {"ca": 215.6593780517578, "camera_make": "SAMSUNG", "camera_model": "SM-N9005", "captured_at": "2018-05-14T12:40:54.705Z", "key": "NACePUrxAPs2Wo2GS9fiRw", "pano": false, "user_key": "i1FGvYWQoDeMVAlkvDwvUA", "username": "vst"}, "geometry": {"type": "Point", "coordinates": [19.062580349456994, 47.416780239585364]}}, {"type": "Feature", "properties": {"ca": 38.8851318359375, "camera_make": "SAMSUNG", "camera_model": "SM-N9005", "captured_at": "2018-05-14T12:29:58.969Z", "key": "9C5rYgSH3Bpb_YyjH2wGUQ", "pano": false, "user_key": "i1FGvYWQoDeMVAlkvDwvUA", "username": "vst"}, "geometry": {"type": "Point", "coordinates": [19.06245486278192, 47.41648344915416]}}, {"type": "Feature", "properties": {"ca": 41.229827880859375, "camera_make": "SAMSUNG", "camera_model": "SM-N9005", "captured_at": "2018-05-14T12:29:57.679Z", "key": "8EtytutwoWpBb6gUkVWwDA", "pano": false, "user_key": "i1FGvYWQoDeMVAlkvDwvUA", "username": "vst"}, "geometry": {"type": "Point", "coordinates": [19.062331836883686, 47.41638239388561]}}, {"type": "Feature", "properties": {"ca": 42.865997314453125, "camera_make": "SAMSUNG", "camera_model": "SM-N9005", "captured_at": "2018-05-14T12:29:56.452Z", "key": "PG8fQpEjM0BJdKVn0LuMZQ", "pano": false, "user_key": "i1FGvYWQoDeMVAlkvDwvUA", "username": "vst"}, "geometry": {"type": "Point", "coordinates": [19.06221174358177, 47.4162918973085]}}, {"type": "Feature", "properties": {"ca": 115.53427124023438, "camera_make": "SAMSUNG", "camera_model": "SM-N9005", "captured_at": "2018-05-14T12:28:58.295Z", "key": "M36S2UbKBAepK9d-rSRklQ", "pano": false, "user_key": "i1FGvYWQoDeMVAlkvDwvUA", "username": "vst"}, "geometry": {"type": "Point", "coordinates": [19.06139830788709, 47.41632073456668]}}, {"type": "Feature", "properties": {"ca": 208.12208557128906, "camera_make": "SAMSUNG", "camera_model": "SM-N9005", "captured_at": "2018-05-02T07:49:18.383Z", "key": "VlXKBiKCGKFiWJNJ3UEyFA", "pano": false, "user_key": "i1FGvYWQoDeMVAlkvDwvUA", "username": "vst"}, "geometry": {"type": "Point", "coordinates": [19.06122165876593, 47.416469530264465]}}, {"type": "Feature", "properties": {"ca": 213.1761932373047, "camera_make": "SAMSUNG", "camera_model": "SM-N9005", "captured_at": "2018-05-02T07:49:16.583Z", "key": "-vYOXEFZesfIORIUPePFYA", "pano": false, "user_key": "i1FGvYWQoDeMVAlkvDwvUA", "username": "vst"}, "geometry": {"type": "Point", "coordinates": [19.061324942147166, 47.416591587574544]}}, {"type": "Feature", "properties": {"ca": 207.80239868164062, "camera_make": "SAMSUNG", "camera_model": "SM-N9005", "captured_at": "2018-05-02T07:49:15.480Z", "key": "bMgyAxFCDzApNYTrwVeOrQ", "pano": false, "user_key": "i1FGvYWQoDeMVAlkvDwvUA", "username": "vst"}, "geometry": {"type": "Point", "coordinates": [19.061386341129037, 47.41666243911288]}}, {"type": "Feature", "properties": {"ca": 219.62313842773438, "camera_make": "SAMSUNG", "camera_model": "SM-N9005", "captured_at": "2018-05-02T07:49:14.108Z", "key": "2tT3V6kewff7mEcR1d_iPA", "pano": false, "user_key": "i1FGvYWQoDeMVAlkvDwvUA", "username": "vst"}, "geometry": {"type": "Point", "coordinates": [19.061476077098405, 47.416749026424895]}}, {"type": "Feature", "properties": {"ca": 31.48406982421875, "camera_make": "samsung", "camera_model": "SM-J320FN", "captured_at": "2018-02-24T12:41:47.579Z", "key": "yYhZQvam_tGa78gKD1NpKg", "pano": false, "user_key": "i1FGvYWQoDeMVAlkvDwvUA", "username": "vst"}, "geometry": {"type": "Point", "coordinates": [19.061532628669966, 47.41671703133005]}}, {"type": "Feature", "properties": {"ca": 29.547515869140625, "camera_make": "samsung", "camera_model": "SM-J320FN", "captured_at": "2018-02-24T12:41:46.568Z", "key": "glx1_-z0O8xs7QoBreKeag", "pano": false, "user_key": "i1FGvYWQoDeMVAlkvDwvUA", "username": "vst"}, "geometry": {"type": "Point", "coordinates": [19.061467043811376, 47.416643109037295]}}, {"type": "Feature", "properties": {"ca": 29.90338134765625, "camera_make": "samsung", "camera_model": "SM-J320FN", "captured_at": "2018-02-24T12:41:45.398Z", "key": "5aN9pzf8I2UDnCgIuUm_SQ", "pano": false, "user_key": "i1FGvYWQoDeMVAlkvDwvUA", "username": "vst"}, "geometry": {"type": "Point", "coordinates": [19.061395175776397, 47.416557483850966]}}, {"type": "Feature", "properties": {"ca": 29.36553955078125, "camera_make": "samsung", "camera_model": "SM-J320FN", "captured_at": "2018-02-24T12:41:44.465Z", "key": "caAq0PQIQLX35b6ct1MGrg", "pano": false, "user_key": "i1FGvYWQoDeMVAlkvDwvUA", "username": "vst"}, "geometry": {"type": "Point", "coordinates": [19.061339516216208, 47.41649132702702]}}, {"type": "Feature", "properties": {"ca": 29.316070556640625, "camera_make": "samsung", "camera_model": "SM-J320FN", "captured_at": "2018-02-24T12:41:43.479Z", "key": "IX5pwHZ9WMz2LVdew3WetA", "pano": false, "user_key": "i1FGvYWQoDeMVAlkvDwvUA", "username": "vst"}, "geometry": {"type": "Point", "coordinates": [19.061289019528886, 47.41643037085379]}}, {"type": "Feature", "properties": {"ca": 29.045318603515625, "camera_make": "samsung", "camera_model": "SM-J320FN", "captured_at": "2018-02-24T12:41:42.573Z", "key": "Mmd1QyngC5r30zT4G38t0w", "pano": false, "user_key": "i1FGvYWQoDeMVAlkvDwvUA", "username": "vst"}, "geometry": {"type": "Point", "coordinates": [19.061232194351533, 47.416361393096224]}}, {"type": "Feature", "properties": {"ca": 28.45263671875, "camera_make": "samsung", "camera_model": "SM-J320FN", "captured_at": "2018-02-24T12:41:41.391Z", "key": "Jpdr3KZ2wgk9nGu9MhXuxg", "pano": false, "user_key": "i1FGvYWQoDeMVAlkvDwvUA", "username": "vst"}, "geometry": {"type": "Point", "coordinates": [19.061191811282583, 47.416311547637406]}}, {"type": "Feature", "properties": {"ca": 210.0763397216797, "camera_make": "samsung", "camera_model": "SM-J320FN", "captured_at": "2018-02-24T12:25:32.676Z", "key": "yYxchaKn3OTzHObLouaFQQ", "pano": false, "user_key": "i1FGvYWQoDeMVAlkvDwvUA", "username": "vst"}, "geometry": {"type": "Point", "coordinates": [19.061202083365515, 47.416450945938095]}}, {"type": "Feature", "properties": {"ca": 203.2616729736328, "camera_make": "samsung", "camera_model": "SM-J320FN", "captured_at": "2018-02-24T12:25:14.496Z", "key": "hwDouXyfF-7rFLpFYioFeA", "pano": false, "user_key": "i1FGvYWQoDeMVAlkvDwvUA", "username": "vst"}, "geometry": {"type": "Point", "coordinates": [19.06135382662012, 47.41663663150547]}}, {"type": "Feature", "properties": {"ca": 213.320556640625, "camera_make": "samsung", "camera_model": "SM-J320FN", "captured_at": "2018-02-24T12:25:11.523Z", "key": "KF9lsH-VPSt1xds6HDcG6g", "pano": false, "user_key": "i1FGvYWQoDeMVAlkvDwvUA", "username": "vst"}, "geometry": {"type": "Point", "coordinates": [19.06136879114956, 47.4166584118006]}}, {"type": "Feature", "properties": {"ca": 209.54612731933594, "camera_make": "samsung", "camera_model": "SM-J320FN", "captured_at": "2018-02-24T12:25:10.524Z", "key": "Aap1DtTJHsYZkIkOTzG8Fw", "pano": false, "user_key": "i1FGvYWQoDeMVAlkvDwvUA", "username": "vst"}, "geometry": {"type": "Point", "coordinates": [19.06139971404218, 47.416691991173536]}}, {"type": "Feature", "properties": {"ca": 211.3531036376953, "camera_make": "samsung", "camera_model": "SM-J320FN", "captured_at": "2018-02-24T12:25:09.586Z", "key": "ZIAktCUcjoY7r8-5MwlXnA", "pano": false, "user_key": "i1FGvYWQoDeMVAlkvDwvUA", "username": "vst"}, "geometry": {"type": "Point", "coordinates": [19.061439126181085, 47.41673831496064]}}, {"type": "Feature", "properties": {"ca": 211.73121643066406, "camera_make": "samsung", "camera_model": "SM-J320FN", "captured_at": "2018-02-24T12:25:08.516Z", "key": "yYW1MU_8RxMrvndzErrqGw", "pano": false, "user_key": "i1FGvYWQoDeMVAlkvDwvUA", "username": "vst"}, "geometry": {"type": "Point", "coordinates": [19.061497136334424, 47.41680269485528]}}, {"type": "Feature", "properties": {"ca": 31.0184326171875, "camera_make": "samsung", "camera_model": "SM-J320FN", "captured_at": "2018-02-11T10:06:26.267Z", "key": "CP3shq5idqM_hp5qHCeMPw", "pano": false, "user_key": "i1FGvYWQoDeMVAlkvDwvUA", "username": "vst"}, "geometry": {"type": "Point", "coordinates": [19.06166143554276, 47.41681854438042]}}, {"type": "Feature", "properties": {"ca": 31.009796142578125, "camera_make": "samsung", "camera_model": "SM-J320FN", "captured_at": "2018-02-11T10:06:25.237Z", "key": "7F24l4v5Ztaiip_8TyFd2w", "pano": false, "user_key": "i1FGvYWQoDeMVAlkvDwvUA", "username": "vst"}, "geometry": {"type": "Point", "coordinates": [19.061562277675876, 47.41670660723753]}}, {"type": "Feature", "properties": {"ca": 31.569305419921875, "camera_make": "samsung", "camera_model": "SM-J320FN", "captured_at": "2018-02-11T10:06:23.116Z", "key": "4z5hTE8sgCNigE0PZP2zag", "pano": false, "user_key": "i1FGvYWQoDeMVAlkvDwvUA", "username": "vst"}, "geometry": {"type": "Point", "coordinates": [19.06133974308341, 47.416460328933454]}}, {"type": "Feature", "properties": {"ca": 31.19171142578125, "camera_make": "samsung", "camera_model": "SM-J320FN", "captured_at": "2018-02-11T10:06:22.326Z", "key": "6XT7CVLp2QeujNMjoz9jTQ", "pano": false, "user_key": "i1FGvYWQoDeMVAlkvDwvUA", "username": "vst"}, "geometry": {"type": "Point", "coordinates": [19.061246031612882, 47.416356558064535]}}, {"type": "Feature", "properties": {"ca": 211.6394805908203, "camera_make": "samsung", "camera_model": "SM-J320FN", "captured_at": "2018-02-11T09:53:48.184Z", "key": "TUUM6TmkczFP2x8_irYhqg", "pano": false, "user_key": "i1FGvYWQoDeMVAlkvDwvUA", "username": "vst"}, "geometry": {"type": "Point", "coordinates": [19.06126573401218, 47.41657227352346]}}, {"type": "Feature", "properties": {"ca": 211.5763702392578, "camera_make": "samsung", "camera_model": "SM-J320FN", "captured_at": "2018-02-11T09:53:47.181Z", "key": "CqLroRYnh-x72jaM8lDn0A", "pano": false, "user_key": "i1FGvYWQoDeMVAlkvDwvUA", "username": "vst"}, "geometry": {"type": "Point", "coordinates": [19.06136729811317, 47.416684237735865]}}, {"type": "Feature", "properties": {"ca": 211.0562744140625, "camera_make": "samsung", "camera_model": "SM-J320FN", "captured_at": "2018-02-11T09:53:46.217Z", "key": "pNRRnhoSmDYAar-Ejd41oQ", "pano": false, "user_key": "i1FGvYWQoDeMVAlkvDwvUA", "username": "vst"}, "geometry": {"type": "Point", "coordinates": [19.06146148922153, 47.41678881497006]}}, {"type": "Feature", "properties": {"ca": 33.726806640625, "camera_make": "SAMSUNG", "camera_model": "SM-N9005", "captured_at": "2017-09-20T12:54:28.687Z", "key": "iaZWIPcKRL8fjfFAS69DyQ", "pano": false, "user_key": "i1FGvYWQoDeMVAlkvDwvUA", "username": "vst"}, "geometry": {"type": "Point", "coordinates": [19.061395790542974, 47.4165662285464]}}, {"type": "Feature", "properties": {"ca": 27.687225341796875, "camera_make": "SAMSUNG", "camera_model": "SM-N9005", "captured_at": "2017-09-20T12:54:27.425Z", "key": "IgKrh0_WWLVHzoitN5PscQ", "pano": false, "user_key": "i1FGvYWQoDeMVAlkvDwvUA", "username": "vst"}, "geometry": {"type": "Point", "coordinates": [19.061318374999928, 47.41647499999999]}}, {"type": "Feature", "properties": {"ca": 36.063323974609375, "camera_make": "SAMSUNG", "camera_model": "SM-N9005", "captured_at": "2017-09-20T12:54:26.119Z", "key": "n7xA2R14ejKgLVwLtmJKyQ", "pano": false, "user_key": "i1FGvYWQoDeMVAlkvDwvUA", "username": "vst"}, "geometry": {"type": "Point", "coordinates": [19.06123508952669, 47.41638412124871]}}, {"type": "Feature", "properties": {"ca": 17.92578125, "camera_make": "SAMSUNG", "camera_model": "SM-N9005", "captured_at": "2017-09-19T09:50:01.502Z", "key": "kAK7-0kN_Uz_K75g3GZb7Q", "pano": false, "user_key": "i1FGvYWQoDeMVAlkvDwvUA", "username": "vst"}, "geometry": {"type": "Point", "coordinates": [19.061683885185175, 47.41682284837964]}}, {"type": "Feature", "properties": {"ca": 29.329559326171875, "camera_make": "SAMSUNG", "camera_model": "SM-N9005", "captured_at": "2017-09-19T09:49:59.449Z", "key": "uGkXMgcJOQ9PrWNyAMtJ9Q", "pano": false, "user_key": "i1FGvYWQoDeMVAlkvDwvUA", "username": "vst"}, "geometry": {"type": "Point", "coordinates": [19.061641335947115, 47.4167775555066]}}, {"type": "Feature", "properties": {"ca": 38.6456298828125, "camera_make": "SAMSUNG", "camera_model": "SM-N9005", "captured_at": "2017-09-19T09:49:58.031Z", "key": "GR1Na1MOLHmER6NDijOpZw", "pano": false, "user_key": "i1FGvYWQoDeMVAlkvDwvUA", "username": "vst"}, "geometry": {"type": "Point", "coordinates": [19.061593480738566, 47.41673102924153]}}, {"type": "Feature", "properties": {"ca": 22.303924560546875, "camera_make": "SAMSUNG", "camera_model": "SM-N9005", "captured_at": "2017-09-19T09:49:56.915Z", "key": "DrB4kTvj6uvmpi391VuyDw", "pano": false, "user_key": "i1FGvYWQoDeMVAlkvDwvUA", "username": "vst"}, "geometry": {"type": "Point", "coordinates": [19.061550562598427, 47.41666668759842]}}, {"type": "Feature", "properties": {"ca": 29.310028076171875, "camera_make": "SAMSUNG", "camera_model": "SM-N9005", "captured_at": "2017-09-19T09:49:55.884Z", "key": "k6IWeuTQ2jeZf0wKbKJdIg", "pano": false, "user_key": "i1FGvYWQoDeMVAlkvDwvUA", "username": "vst"}, "geometry": {"type": "Point", "coordinates": [19.06148477889451, 47.41658529869346]}}, {"type": "Feature", "properties": {"ca": 25.2767333984375, "camera_make": "SAMSUNG", "camera_model": "SM-N9005", "captured_at": "2017-09-19T09:49:54.671Z", "key": "ppwOdNgxe0ut_zb2hCVF-g", "pano": false, "user_key": "i1FGvYWQoDeMVAlkvDwvUA", "username": "vst"}, "geometry": {"type": "Point", "coordinates": [19.061403245266547, 47.416461959738854]}}, {"type": "Feature", "properties": {"ca": 29.69171142578125, "camera_make": "SAMSUNG", "camera_model": "SM-N9005", "captured_at": "2017-09-19T09:49:53.438Z", "key": "BriHKzElW25bAaplcSmddA", "pano": false, "user_key": "i1FGvYWQoDeMVAlkvDwvUA", "username": "vst"}, "geometry": {"type": "Point", "coordinates": [19.06129195742119, 47.41631247708722]}}, {"type": "Feature", "properties": {"ca": 49.581512451171875, "camera_make": "NOKIA", "camera_model": "RM-825_eu_hungary_398", "captured_at": "2016-10-03T13:16:10.414Z", "key": "S9VS2x5tf6Xdod2EZy_Qzg", "pano": false, "user_key": "BHEYec7Dik3yfmQ5365Anw", "username": "beyazg"}, "geometry": {"type": "Point", "coordinates": [19.061388010159135, 47.416686583310366]}}, {"type": "Feature", "properties": {"ca": 45.702667236328125, "camera_make": "NOKIA", "camera_model": "RM-825_eu_hungary_398", "captured_at": "2016-10-03T13:16:06.801Z", "key": "MThMb9bQLFR_CFxOZ22wxw", "pano": false, "user_key": "BHEYec7Dik3yfmQ5365Anw", "username": "beyazg"}, "geometry": {"type": "Point", "coordinates": [19.061486162245274, 47.416801750659886]}}, {"type": "Feature", "properties": {"ca": 211.50412750244095, "camera_make": "NOKIA", "camera_model": "RM-825_eu_hungary_398", "captured_at": "2016-09-30T15:55:17.615Z", "key": "2Tk4JPHfkKRjPVDfDzSdKQ", "pano": false, "user_key": "BHEYec7Dik3yfmQ5365Anw", "username": "beyazg"}, "geometry": {"type": "Point", "coordinates": [19.0612988267094, 47.4164627864957]}}, {"type": "Feature", "properties": {"ca": 246.07040405273403, "camera_make": "NOKIA", "camera_model": "RM-825_eu_hungary_398", "captured_at": "2016-09-30T15:55:13.956Z", "key": "Yk9B1I0RDyaQ7jaVNk0pfg", "pano": false, "user_key": "BHEYec7Dik3yfmQ5365Anw", "username": "beyazg"}, "geometry": {"type": "Point", "coordinates": [19.061411479488, 47.416672334075]}}, {"type": "Feature", "properties": {"ca": 242.90911865234398, "camera_make": "NOKIA", "camera_model": "RM-825_eu_hungary_398", "captured_at": "2016-09-30T15:55:04.430Z", "key": "BBrooFboPoP3j8eTYd5HVw", "pano": false, "user_key": "BHEYec7Dik3yfmQ5365Anw", "username": "beyazg"}, "geometry": {"type": "Point", "coordinates": [19.0614908561111, 47.4167429935187]}}, {"type": "Feature", "properties": {"ca": 35.05081679868778, "camera_make": "SAMSUNG", "camera_model": "GT-I9100", "captured_at": "2016-07-26T11:18:28.412Z", "key": "QGW-DFwz75EWytakoIpMCg", "pano": false, "user_key": "HUmuI_w604pLKD6tTGh04Q", "username": "koles\u00e1r"}, "geometry": {"type": "Point", "coordinates": [19.061506194993854, 47.41665192414075]}}, {"type": "Feature", "properties": {"ca": 33.421292276031465, "camera_make": "SAMSUNG", "camera_model": "GT-I9100", "captured_at": "2016-07-26T11:18:27.131Z", "key": "z7XqbWhwoDDucHV1b4TQLw", "pano": false, "user_key": "HUmuI_w604pLKD6tTGh04Q", "username": "koles\u00e1r"}, "geometry": {"type": "Point", "coordinates": [19.06146939843893, 47.41663147229701]}}, {"type": "Feature", "properties": {"ca": 35.765465482760646, "camera_make": "SAMSUNG", "camera_model": "GT-I9100", "captured_at": "2016-07-26T11:18:26.195Z", "key": "AUuVU9IlOghVtG5gUWUBHQ", "pano": false, "user_key": "HUmuI_w604pLKD6tTGh04Q", "username": "koles\u00e1r"}, "geometry": {"type": "Point", "coordinates": [19.061294049024582, 47.41640708874911]}}, {"type": "Feature", "properties": {"ca": 33.6361174516681, "camera_make": "SAMSUNG", "camera_model": "GT-I9100", "captured_at": "2016-07-26T11:18:24.918Z", "key": "uipbXCi3T9a8G-P4IhFh6w", "pano": false, "user_key": "HUmuI_w604pLKD6tTGh04Q", "username": "koles\u00e1r"}, "geometry": {"type": "Point", "coordinates": [19.061331935226917, 47.41646463051438]}}, {"type": "Feature", "properties": {"ca": 34.676170251709664, "camera_make": "SAMSUNG", "camera_model": "GT-I9100", "captured_at": "2016-07-26T11:18:22.710Z", "key": "t1HKwCADHxZXVVmIfI0PGw", "pano": false, "user_key": "HUmuI_w604pLKD6tTGh04Q", "username": "koles\u00e1r"}, "geometry": {"type": "Point", "coordinates": [19.061201428994536, 47.416306673549116]}}, {"type": "Feature", "properties": {"ca": 289.0375965336864, "camera_make": "SAMSUNG", "camera_model": "GT-I8262", "captured_at": "2015-12-19T12:53:43.305Z", "key": "ujrsikgB8SOf24CkaoUK1Q", "pano": false, "user_key": "Rxi6DT6sw24wzcWTCneoLQ", "username": "es\u00e1ndor"}, "geometry": {"type": "Point", "coordinates": [19.06134308, 47.41640207]}}, {"type": "Feature", "properties": {"ca": 315.7272265123818, "camera_make": "SAMSUNG", "camera_model": "GT-I8262", "captured_at": "2015-12-19T12:53:40.772Z", "key": "n4ah4RIQ9czPGwYc-3JhlQ", "pano": false, "user_key": "Rxi6DT6sw24wzcWTCneoLQ", "username": "es\u00e1ndor"}, "geometry": {"type": "Point", "coordinates": [19.06149576, 47.41635601]}}, {"type": "Feature", "properties": {"ca": 222.08516315256713, "camera_make": "SAMSUNG", "camera_model": "GT-I8262", "captured_at": "2015-12-19T12:51:31.189Z", "key": "qeKOc9UIqU-7Yzy0x00cQw", "pano": false, "user_key": "Rxi6DT6sw24wzcWTCneoLQ", "username": "es\u00e1ndor"}, "geometry": {"type": "Point", "coordinates": [19.06238354, 47.41658625]}}, {"type": "Feature", "properties": {"ca": 231.73098337950557, "camera_make": "SAMSUNG", "camera_model": "GT-I8262", "captured_at": "2015-12-19T12:51:28.591Z", "key": "xpnEJCnch-tAHXq99q-_eQ", "pano": false, "user_key": "Rxi6DT6sw24wzcWTCneoLQ", "username": "es\u00e1ndor"}, "geometry": {"type": "Point", "coordinates": [19.06254591, 47.41672674]}}, {"type": "Feature", "properties": {"ca": 40.18035690955094, "camera_make": "SAMSUNG", "camera_model": "GT-I8262", "captured_at": "2015-12-19T11:09:14.233Z", "key": "8QQzSd3K-ziegpUWHB1IDA", "pano": false, "user_key": "Rxi6DT6sw24wzcWTCneoLQ", "username": "es\u00e1ndor"}, "geometry": {"type": "Point", "coordinates": [19.06252611, 47.41646863]}}, {"type": "Feature", "properties": {"ca": 40.50854269472268, "camera_make": "SAMSUNG", "camera_model": "GT-I8262", "captured_at": "2015-12-19T11:09:12.671Z", "key": "3YahInXg8MIDWPzsDGoDQw", "pano": false, "user_key": "Rxi6DT6sw24wzcWTCneoLQ", "username": "es\u00e1ndor"}, "geometry": {"type": "Point", "coordinates": [19.06235732, 47.41634008]}}, {"type": "Feature", "properties": {"ca": 213.7702021519508, "camera_make": "SAMSUNG", "camera_model": "GT-I8262", "captured_at": "2015-11-25T09:20:27.603Z", "key": "5pwApJwL_pHmgyJNhisQHg", "pano": false, "user_key": "Rxi6DT6sw24wzcWTCneoLQ", "username": "es\u00e1ndor"}, "geometry": {"type": "Point", "coordinates": [19.0613473, 47.41665588]}}, {"type": "Feature", "properties": {"ca": 228.38174164651605, "camera_make": "SAMSUNG", "camera_model": "GT-I8262", "captured_at": "2015-08-23T17:54:27.804Z", "key": "SMZGahRG7LjPSZn65S5Yqw", "pano": false, "user_key": "Rxi6DT6sw24wzcWTCneoLQ", "username": "es\u00e1ndor"}, "geometry": {"type": "Point", "coordinates": [19.0619854, 47.41629906]}}, {"type": "Feature", "properties": {"ca": 227.46507299782843, "camera_make": "SAMSUNG", "camera_model": "GT-I8262", "captured_at": "2015-08-23T17:54:25.205Z", "key": "pxLLfhOus1TUEAo7kWQ5lg", "pano": false, "user_key": "Rxi6DT6sw24wzcWTCneoLQ", "username": "es\u00e1ndor"}, "geometry": {"type": "Point", "coordinates": [19.06201434, 47.41631929]}}]}