{"type": "FeatureCollection", "features": [{"type": "Feature", "properties": {"ca": 112.47900390625, "camera_make": "Apple", "camera_model": "iPhone", "captured_at": "2018-08-16T13:34:19.168Z", "key": "09Wvc5HBxYbFecBBarBZwQ", "pano": false, "user_key": "YuQrtsCxGUoXXc_vUZLzPA", "username": "szili"}, "geometry": {"type": "Point", "coordinates": [19.10737138243309, 47.48654073574346]}}, {"type": "Feature", "properties": {"ca": 109.91558837890625, "camera_make": "Apple", "camera_model": "iPhone", "captured_at": "2018-08-16T13:34:17.181Z", "key": "z9pIrIhzW0KB6o3L3xS6mw", "pano": false, "user_key": "YuQrtsCxGUoXXc_vUZLzPA", "username": "szili"}, "geometry": {"type": "Point", "coordinates": [19.107158985006723, 47.48659878042292]}}, {"type": "Feature", "properties": {"ca": 110.457275390625, "camera_make": "Apple", "camera_model": "iPhone", "captured_at": "2018-08-16T13:34:15.161Z", "key": "ZaVeV6Yx25sOJxTxnlPLsg", "pano": false, "user_key": "YuQrtsCxGUoXXc_vUZLzPA", "username": "szili"}, "geometry": {"type": "Point", "coordinates": [19.1069961246281, 47.486641276672]}}, {"type": "Feature", "properties": {"ca": 114.01968383789062, "camera_make": "Apple", "camera_model": "iPhone", "captured_at": "2018-08-16T13:34:13.133Z", "key": "bJ3nQe32jlEcR1H1a_MRsw", "pano": false, "user_key": "YuQrtsCxGUoXXc_vUZLzPA", "username": "szili"}, "geometry": {"type": "Point", "coordinates": [19.10688414240173, 47.486669481776175]}}, {"type": "Feature", "properties": {"ca": 114.06646728515625, "camera_make": "Apple", "camera_model": "iPhone", "captured_at": "2018-08-16T13:34:10.107Z", "key": "ls0KjnDOrosI5ViQJyr18g", "pano": false, "user_key": "YuQrtsCxGUoXXc_vUZLzPA", "username": "szili"}, "geometry": {"type": "Point", "coordinates": [19.106744583713922, 47.48671038546365]}}, {"type": "Feature", "properties": {"ca": 109.31298828125, "camera_make": "Apple", "camera_model": "iPhone", "captured_at": "2018-08-16T13:33:02.175Z", "key": "zLnagnfeIntUHzPBFYVRiQ", "pano": false, "user_key": "YuQrtsCxGUoXXc_vUZLzPA", "username": "szili"}, "geometry": {"type": "Point", "coordinates": [19.106593038904577, 47.486755186736104]}}, {"type": "Feature", "properties": {"ca": 114.75625610351562, "camera_make": "Apple", "camera_model": "iPhone", "captured_at": "2018-08-16T13:32:59.201Z", "key": "q6Us1Mowg3T2MeXcI_75Xg", "pano": false, "user_key": "YuQrtsCxGUoXXc_vUZLzPA", "username": "szili"}, "geometry": {"type": "Point", "coordinates": [19.106433279830128, 47.48679512650472]}}, {"type": "Feature", "properties": {"ca": 116.3463134765625, "camera_make": "Apple", "camera_model": "iPhone", "captured_at": "2018-08-16T13:32:56.162Z", "key": "ngpjObGNSAajm03t0Tntbw", "pano": false, "user_key": "YuQrtsCxGUoXXc_vUZLzPA", "username": "szili"}, "geometry": {"type": "Point", "coordinates": [19.106256673130304, 47.48684994415146]}}, {"type": "Feature", "properties": {"ca": 114.77972412109375, "camera_make": "Apple", "camera_model": "iPhone", "captured_at": "2018-08-16T13:32:54.193Z", "key": "7k4KLhZAHlApEC0uNuYFJg", "pano": false, "user_key": "YuQrtsCxGUoXXc_vUZLzPA", "username": "szili"}, "geometry": {"type": "Point", "coordinates": [19.10613832065752, 47.486888626634595]}}, {"type": "Feature", "properties": {"ca": 109.99163818359375, "camera_make": "Apple", "camera_model": "iPhone", "captured_at": "2018-08-16T13:32:51.177Z", "key": "BQksYRp8QB9qruqNuvqPEg", "pano": false, "user_key": "YuQrtsCxGUoXXc_vUZLzPA", "username": "szili"}, "geometry": {"type": "Point", "coordinates": [19.106004713120967, 47.486929111226914]}}, {"type": "Feature", "properties": {"ca": 114.8176770686249, "camera_make": "", "camera_model": "", "captured_at": "2018-08-02T10:35:37.248Z", "key": "KM8jc11XwimCp0mJnGvm_g", "pano": false, "user_key": "-uS--wGRrzA9yPvonZ_W4A", "username": "teamwork"}, "geometry": {"type": "Point", "coordinates": [19.107405908607998, 47.48652802856]}}, {"type": "Feature", "properties": {"ca": 123.71771635749917, "camera_make": "", "camera_model": "", "captured_at": "2018-08-02T10:35:36.851Z", "key": "SzzDNvnWB2xlrVRJGa6axQ", "pano": false, "user_key": "-uS--wGRrzA9yPvonZ_W4A", "username": "teamwork"}, "geometry": {"type": "Point", "coordinates": [19.107382429968, 47.486536413936]}}, {"type": "Feature", "properties": {"ca": 123.71771635749917, "camera_make": "", "camera_model": "", "captured_at": "2018-08-02T10:35:36.418Z", "key": "Ut6ixlVZOWPZXyb3HZU6GA", "pano": false, "user_key": "-uS--wGRrzA9yPvonZ_W4A", "username": "teamwork"}, "geometry": {"type": "Point", "coordinates": [19.107360335034, 47.486546378317996]}}, {"type": "Feature", "properties": {"ca": 134.6117522095103, "camera_make": "", "camera_model": "", "captured_at": "2018-08-02T10:35:35.985Z", "key": "DgRZitM4Dw-hIcZExs5qfg", "pano": false, "user_key": "-uS--wGRrzA9yPvonZ_W4A", "username": "teamwork"}, "geometry": {"type": "Point", "coordinates": [19.107338337735, 47.486556441510004]}}, {"type": "Feature", "properties": {"ca": 134.6117522095103, "camera_make": "", "camera_model": "", "captured_at": "2018-08-02T10:35:35.564Z", "key": "bMpXB1fE5Hq_vlPnnwaLDw", "pano": false, "user_key": "-uS--wGRrzA9yPvonZ_W4A", "username": "teamwork"}, "geometry": {"type": "Point", "coordinates": [19.107319416990002, 47.486569055340006]}}, {"type": "Feature", "properties": {"ca": 134.6117522095103, "camera_make": "", "camera_model": "", "captured_at": "2018-08-02T10:35:35.144Z", "key": "7ZOSIsB1xhAOW4r5nbxZPw", "pano": false, "user_key": "-uS--wGRrzA9yPvonZ_W4A", "username": "teamwork"}, "geometry": {"type": "Point", "coordinates": [19.107300496245003, 47.48658166917]}}, {"type": "Feature", "properties": {"ca": 159.13317606587657, "camera_make": "", "camera_model": "", "captured_at": "2018-08-02T10:35:34.708Z", "key": "Az1TOcw_TiO7V0ZFZL7tJg", "pano": false, "user_key": "-uS--wGRrzA9yPvonZ_W4A", "username": "teamwork"}, "geometry": {"type": "Point", "coordinates": [19.10728757875, 47.486597383125]}}, {"type": "Feature", "properties": {"ca": 159.13317606587657, "camera_make": "", "camera_model": "", "captured_at": "2018-08-02T10:35:34.277Z", "key": "ICYUtQ0GOsZnVh8BuTaeIg", "pano": false, "user_key": "-uS--wGRrzA9yPvonZ_W4A", "username": "teamwork"}, "geometry": {"type": "Point", "coordinates": [19.107278100511998, 47.486614185456]}}, {"type": "Feature", "properties": {"ca": 139.43760980071187, "camera_make": "", "camera_model": "", "captured_at": "2018-08-02T10:35:33.663Z", "key": "USaelLJquRud0OSRP922cA", "pano": false, "user_key": "-uS--wGRrzA9yPvonZ_W4A", "username": "teamwork"}, "geometry": {"type": "Point", "coordinates": [19.107265599128, 47.48663005332]}}, {"type": "Feature", "properties": {"ca": 128.0761807534841, "camera_make": "", "camera_model": "", "captured_at": "2018-08-02T10:34:24.196Z", "key": "BCTfV7xRPPy7V_xlseiI7A", "pano": false, "user_key": "-uS--wGRrzA9yPvonZ_W4A", "username": "teamwork"}, "geometry": {"type": "Point", "coordinates": [19.107251347164, 47.486645227972]}}, {"type": "Feature", "properties": {"ca": 115.39164203837515, "camera_make": "", "camera_model": "", "captured_at": "2018-08-02T10:34:22.849Z", "key": "D5AWsIwM3573pGw9mkPDJA", "pano": false, "user_key": "-uS--wGRrzA9yPvonZ_W4A", "username": "teamwork"}, "geometry": {"type": "Point", "coordinates": [19.107211016716, 47.486668560676]}}, {"type": "Feature", "properties": {"ca": 115.39164203837515, "camera_make": "", "camera_model": "", "captured_at": "2018-08-02T10:34:22.396Z", "key": "A0cFdZ2zBi-oNMN8OhhqpQ", "pano": false, "user_key": "-uS--wGRrzA9yPvonZ_W4A", "username": "teamwork"}, "geometry": {"type": "Point", "coordinates": [19.107187028492, 47.486676255012]}}, {"type": "Feature", "properties": {"ca": 119.24570146107527, "camera_make": "", "camera_model": "", "captured_at": "2018-08-02T10:34:21.961Z", "key": "5lL8NKbOEdU1AROgFXpfTw", "pano": false, "user_key": "-uS--wGRrzA9yPvonZ_W4A", "username": "teamwork"}, "geometry": {"type": "Point", "coordinates": [19.107163135312, 47.486684083936005]}}, {"type": "Feature", "properties": {"ca": 119.24570146107527, "camera_make": "", "camera_model": "", "captured_at": "2018-08-02T10:34:21.648Z", "key": "jIo688dEj26KquAlhHCi9Q", "pano": false, "user_key": "-uS--wGRrzA9yPvonZ_W4A", "username": "teamwork"}, "geometry": {"type": "Point", "coordinates": [19.10713996273, 47.48669285194]}}, {"type": "Feature", "properties": {"ca": 119.24570146107527, "camera_make": "", "camera_model": "", "captured_at": "2018-08-02T10:34:21.335Z", "key": "qFICPrlixqpRF41N0sm_5g", "pano": false, "user_key": "-uS--wGRrzA9yPvonZ_W4A", "username": "teamwork"}, "geometry": {"type": "Point", "coordinates": [19.107116790222, 47.486701619916]}}, {"type": "Feature", "properties": {"ca": 119.24570146107527, "camera_make": "", "camera_model": "", "captured_at": "2018-08-02T10:34:21.021Z", "key": "O-2hdjn9ab-lhtn37UhziQ", "pano": false, "user_key": "-uS--wGRrzA9yPvonZ_W4A", "username": "teamwork"}, "geometry": {"type": "Point", "coordinates": [19.107093617714, 47.486710387892]}}, {"type": "Feature", "properties": {"ca": 113.56464979789405, "camera_make": "", "camera_model": "", "captured_at": "2018-08-02T10:34:20.761Z", "key": "7NfxlT9zyUdjEo4hE2qz9Q", "pano": false, "user_key": "-uS--wGRrzA9yPvonZ_W4A", "username": "teamwork"}, "geometry": {"type": "Point", "coordinates": [19.107069353995, 47.486717674612]}}, {"type": "Feature", "properties": {"ca": 113.56464979789405, "camera_make": "", "camera_model": "", "captured_at": "2018-08-02T10:34:20.505Z", "key": "ULnwsvybZCe0p0B_Gz7EKw", "pano": false, "user_key": "-uS--wGRrzA9yPvonZ_W4A", "username": "teamwork"}, "geometry": {"type": "Point", "coordinates": [19.1070450168, 47.486724847679994]}}, {"type": "Feature", "properties": {"ca": 113.56464979789405, "camera_make": "", "camera_model": "", "captured_at": "2018-08-02T10:34:20.249Z", "key": "w1MV_12apH3qdrWq-WxeRw", "pano": false, "user_key": "-uS--wGRrzA9yPvonZ_W4A", "username": "teamwork"}, "geometry": {"type": "Point", "coordinates": [19.10702067951, 47.486732020776]}}, {"type": "Feature", "properties": {"ca": 112.63797361183913, "camera_make": "", "camera_model": "", "captured_at": "2018-08-02T10:34:19.993Z", "key": "vWmiHAI5b48efkhWSKsxXw", "pano": false, "user_key": "-uS--wGRrzA9yPvonZ_W4A", "username": "teamwork"}, "geometry": {"type": "Point", "coordinates": [19.10699633769, 47.486739186651]}}, {"type": "Feature", "properties": {"ca": 112.63797361183913, "camera_make": "", "camera_model": "", "captured_at": "2018-08-02T10:34:19.771Z", "key": "WwZgZlEZ_iN268LYdSwhrA", "pano": false, "user_key": "-uS--wGRrzA9yPvonZ_W4A", "username": "teamwork"}, "geometry": {"type": "Point", "coordinates": [19.10697183288, 47.486746092551996]}}, {"type": "Feature", "properties": {"ca": 112.63797361183913, "camera_make": "", "camera_model": "", "captured_at": "2018-08-02T10:34:19.548Z", "key": "tkUQmiGrNr2ujECla_7szA", "pano": false, "user_key": "-uS--wGRrzA9yPvonZ_W4A", "username": "teamwork"}, "geometry": {"type": "Point", "coordinates": [19.10694732796, 47.48675299848401]}}, {"type": "Feature", "properties": {"ca": 112.63797361183913, "camera_make": "", "camera_model": "", "captured_at": "2018-08-02T10:34:19.325Z", "key": "Plm9loct2nI62JrN9c8acg", "pano": false, "user_key": "-uS--wGRrzA9yPvonZ_W4A", "username": "teamwork"}, "geometry": {"type": "Point", "coordinates": [19.10692282315, 47.486759904385]}}, {"type": "Feature", "properties": {"ca": 112.63797361183913, "camera_make": "", "camera_model": "", "captured_at": "2018-08-02T10:34:19.102Z", "key": "BwgGADd3HlwjZ9ixb75U_g", "pano": false, "user_key": "-uS--wGRrzA9yPvonZ_W4A", "username": "teamwork"}, "geometry": {"type": "Point", "coordinates": [19.106898318229998, 47.486766810317]}}, {"type": "Feature", "properties": {"ca": 116.45140377014394, "camera_make": "", "camera_model": "", "captured_at": "2018-08-02T10:34:18.889Z", "key": "oA5Jyjp8tfMW5b8pd5aQ2g", "pano": false, "user_key": "-uS--wGRrzA9yPvonZ_W4A", "username": "teamwork"}, "geometry": {"type": "Point", "coordinates": [19.106874193252, 47.486774305717]}}, {"type": "Feature", "properties": {"ca": 116.45140377014394, "camera_make": "", "camera_model": "", "captured_at": "2018-08-02T10:34:18.684Z", "key": "oFuHC92oesqihoPbnmCQ4g", "pano": false, "user_key": "-uS--wGRrzA9yPvonZ_W4A", "username": "teamwork"}, "geometry": {"type": "Point", "coordinates": [19.106850418704, 47.486782298884]}}, {"type": "Feature", "properties": {"ca": 116.45140377014394, "camera_make": "", "camera_model": "", "captured_at": "2018-08-02T10:34:18.479Z", "key": "DyM7Mmnt48omt0AM5DY2Xg", "pano": false, "user_key": "-uS--wGRrzA9yPvonZ_W4A", "username": "teamwork"}, "geometry": {"type": "Point", "coordinates": [19.106826644039998, 47.48679029209001]}}, {"type": "Feature", "properties": {"ca": 116.45140377014394, "camera_make": "", "camera_model": "", "captured_at": "2018-08-02T10:34:18.274Z", "key": "elJ4AvckZOuc6EycBji3Cw", "pano": false, "user_key": "-uS--wGRrzA9yPvonZ_W4A", "username": "teamwork"}, "geometry": {"type": "Point", "coordinates": [19.106802869492, 47.486798285257]}}, {"type": "Feature", "properties": {"ca": 116.45140377014394, "camera_make": "", "camera_model": "", "captured_at": "2018-08-02T10:34:18.069Z", "key": "G8zGCXCVQOyRsfhnFchAXA", "pano": false, "user_key": "-uS--wGRrzA9yPvonZ_W4A", "username": "teamwork"}, "geometry": {"type": "Point", "coordinates": [19.106779094827996, 47.486806278463]}}, {"type": "Feature", "properties": {"ca": 114.11684549444203, "camera_make": "", "camera_model": "", "captured_at": "2018-08-02T10:34:17.865Z", "key": "-jXyWSBkN9hhpIl3HqlcZQ", "pano": false, "user_key": "-uS--wGRrzA9yPvonZ_W4A", "username": "teamwork"}, "geometry": {"type": "Point", "coordinates": [19.106755012468998, 47.486813836564]}}, {"type": "Feature", "properties": {"ca": 114.11684549444203, "camera_make": "", "camera_model": "", "captured_at": "2018-08-02T10:34:17.662Z", "key": "trulSWyjG52tZkkxUo542Q", "pano": false, "user_key": "-uS--wGRrzA9yPvonZ_W4A", "username": "teamwork"}, "geometry": {"type": "Point", "coordinates": [19.106730778118997, 47.486821167963996]}}, {"type": "Feature", "properties": {"ca": 114.11684549444203, "camera_make": "", "camera_model": "", "captured_at": "2018-08-02T10:34:17.458Z", "key": "w-5AUZbJlyrX14uoVMK4DQ", "pano": false, "user_key": "-uS--wGRrzA9yPvonZ_W4A", "username": "teamwork"}, "geometry": {"type": "Point", "coordinates": [19.10670654365, 47.486828499400005]}}, {"type": "Feature", "properties": {"ca": 114.11684549444203, "camera_make": "", "camera_model": "", "captured_at": "2018-08-02T10:34:17.254Z", "key": "NgLA-I2Xvv1i9nDNmxL25g", "pano": false, "user_key": "-uS--wGRrzA9yPvonZ_W4A", "username": "teamwork"}, "geometry": {"type": "Point", "coordinates": [19.1066823093, 47.4868358308]}}, {"type": "Feature", "properties": {"ca": 114.11684549444203, "camera_make": "", "camera_model": "", "captured_at": "2018-08-02T10:34:17.051Z", "key": "twuHAS7Cc4UgoHd1G6n3ew", "pano": false, "user_key": "-uS--wGRrzA9yPvonZ_W4A", "username": "teamwork"}, "geometry": {"type": "Point", "coordinates": [19.10665807495, 47.4868431622]}}, {"type": "Feature", "properties": {"ca": 117.5453687114009, "camera_make": "", "camera_model": "", "captured_at": "2018-08-02T10:34:16.855Z", "key": "rFKSGZrBhdwXv58oDr6FLw", "pano": false, "user_key": "-uS--wGRrzA9yPvonZ_W4A", "username": "teamwork"}, "geometry": {"type": "Point", "coordinates": [19.106634348796, 47.486851221326006]}}, {"type": "Feature", "properties": {"ca": 117.5453687114009, "camera_make": "", "camera_model": "", "captured_at": "2018-08-02T10:34:16.662Z", "key": "zC_XC2FSQGiAhBHfHfelqg", "pano": false, "user_key": "-uS--wGRrzA9yPvonZ_W4A", "username": "teamwork"}, "geometry": {"type": "Point", "coordinates": [19.106610803284, 47.486859520154]}}, {"type": "Feature", "properties": {"ca": 117.5453687114009, "camera_make": "", "camera_model": "", "captured_at": "2018-08-02T10:34:16.469Z", "key": "0tE-CdC98Jvwped5j581dw", "pano": false, "user_key": "-uS--wGRrzA9yPvonZ_W4A", "username": "teamwork"}, "geometry": {"type": "Point", "coordinates": [19.10658725765, 47.48686781902501]}}, {"type": "Feature", "properties": {"ca": 117.5453687114009, "camera_make": "", "camera_model": "", "captured_at": "2018-08-02T10:34:16.276Z", "key": "jdrdcl91s5yDfvZT9xqYZQ", "pano": false, "user_key": "-uS--wGRrzA9yPvonZ_W4A", "username": "teamwork"}, "geometry": {"type": "Point", "coordinates": [19.106563712015998, 47.486876117895996]}}, {"type": "Feature", "properties": {"ca": 117.5453687114009, "camera_make": "", "camera_model": "", "captured_at": "2018-08-02T10:34:16.083Z", "key": "HFc8baAXzA1H0_kSAXT3Tw", "pano": false, "user_key": "-uS--wGRrzA9yPvonZ_W4A", "username": "teamwork"}, "geometry": {"type": "Point", "coordinates": [19.106540166381997, 47.486884416767]}}, {"type": "Feature", "properties": {"ca": 114.98944953752789, "camera_make": "", "camera_model": "", "captured_at": "2018-08-02T10:34:15.892Z", "key": "MtgnTl-OoJl6DzIRVM5QHA", "pano": false, "user_key": "-uS--wGRrzA9yPvonZ_W4A", "username": "teamwork"}, "geometry": {"type": "Point", "coordinates": [19.106516318544, 47.486892309119995]}}, {"type": "Feature", "properties": {"ca": 114.98944953752789, "camera_make": "", "camera_model": "", "captured_at": "2018-08-02T10:34:15.702Z", "key": "Raij_lB3atPG4nhBar95lQ", "pano": false, "user_key": "-uS--wGRrzA9yPvonZ_W4A", "username": "teamwork"}, "geometry": {"type": "Point", "coordinates": [19.106492251409, 47.48689988932]}}, {"type": "Feature", "properties": {"ca": 114.98944953752789, "camera_make": "", "camera_model": "", "captured_at": "2018-08-02T10:34:15.513Z", "key": "8Mg77NQotSWopqU64O-V5w", "pano": false, "user_key": "-uS--wGRrzA9yPvonZ_W4A", "username": "teamwork"}, "geometry": {"type": "Point", "coordinates": [19.106468184146998, 47.486907469559995]}}, {"type": "Feature", "properties": {"ca": 114.98944953752789, "camera_make": "", "camera_model": "", "captured_at": "2018-08-02T10:34:15.323Z", "key": "RKs1ALghusc4K9XSAM31Rg", "pano": false, "user_key": "-uS--wGRrzA9yPvonZ_W4A", "username": "teamwork"}, "geometry": {"type": "Point", "coordinates": [19.106444116885, 47.4869150498]}}, {"type": "Feature", "properties": {"ca": 114.98944953752789, "camera_make": "", "camera_model": "", "captured_at": "2018-08-02T10:34:15.134Z", "key": "NsxNS2aiiATOkr833g6Ixg", "pano": false, "user_key": "-uS--wGRrzA9yPvonZ_W4A", "username": "teamwork"}, "geometry": {"type": "Point", "coordinates": [19.106420049623, 47.48692263004]}}, {"type": "Feature", "properties": {"ca": 117.82000591314284, "camera_make": "", "camera_model": "", "captured_at": "2018-08-02T10:34:14.946Z", "key": "kvrq1wbg767uFsz7BcBpOw", "pano": false, "user_key": "-uS--wGRrzA9yPvonZ_W4A", "username": "teamwork"}, "geometry": {"type": "Point", "coordinates": [19.106396145714, 47.486930444163995]}}, {"type": "Feature", "properties": {"ca": 117.82000591314284, "camera_make": "", "camera_model": "", "captured_at": "2018-08-02T10:34:14.764Z", "key": "wt-yFtl0IsvaYO7YLdjt3g", "pano": false, "user_key": "-uS--wGRrzA9yPvonZ_W4A", "username": "teamwork"}, "geometry": {"type": "Point", "coordinates": [19.106372658942, 47.486938819292]}}, {"type": "Feature", "properties": {"ca": 117.82000591314284, "camera_make": "", "camera_model": "", "captured_at": "2018-08-02T10:34:14.582Z", "key": "nQrTXxJ_O-xy_LJ8JCIarQ", "pano": false, "user_key": "-uS--wGRrzA9yPvonZ_W4A", "username": "teamwork"}, "geometry": {"type": "Point", "coordinates": [19.10634917217, 47.48694719442]}}, {"type": "Feature", "properties": {"ca": 117.82000591314284, "camera_make": "", "camera_model": "", "captured_at": "2018-08-02T10:34:14.400Z", "key": "7w9sv1DqyPoc39CWRFFMFA", "pano": false, "user_key": "-uS--wGRrzA9yPvonZ_W4A", "username": "teamwork"}, "geometry": {"type": "Point", "coordinates": [19.106325685398, 47.486955569548]}}, {"type": "Feature", "properties": {"ca": 117.82000591314284, "camera_make": "", "camera_model": "", "captured_at": "2018-08-02T10:34:14.218Z", "key": "Aw40OAQW1TuzqNduYXUAwg", "pano": false, "user_key": "-uS--wGRrzA9yPvonZ_W4A", "username": "teamwork"}, "geometry": {"type": "Point", "coordinates": [19.106302198626, 47.486963944676]}}, {"type": "Feature", "properties": {"ca": 117.82000591314284, "camera_make": "", "camera_model": "", "captured_at": "2018-08-02T10:34:14.036Z", "key": "Du1upz9TLtXASVtWS3Y2YQ", "pano": false, "user_key": "-uS--wGRrzA9yPvonZ_W4A", "username": "teamwork"}, "geometry": {"type": "Point", "coordinates": [19.106278711854, 47.486972319803996]}}, {"type": "Feature", "properties": {"ca": 117.60700705250008, "camera_make": "", "camera_model": "", "captured_at": "2018-08-02T10:34:13.858Z", "key": "yGIpiqDhnJJdgqCeKZb_2A", "pano": false, "user_key": "-uS--wGRrzA9yPvonZ_W4A", "username": "teamwork"}, "geometry": {"type": "Point", "coordinates": [19.10625518848, 47.48698064767999]}}, {"type": "Feature", "properties": {"ca": 117.60700705250008, "camera_make": "", "camera_model": "", "captured_at": "2018-08-02T10:34:13.681Z", "key": "3uPJeRSnQPriLNbUTPhuTQ", "pano": false, "user_key": "-uS--wGRrzA9yPvonZ_W4A", "username": "teamwork"}, "geometry": {"type": "Point", "coordinates": [19.106231655992, 47.486988963672]}}, {"type": "Feature", "properties": {"ca": 117.60700705250008, "camera_make": "", "camera_model": "", "captured_at": "2018-08-02T10:34:13.504Z", "key": "rmramtb5xlvuVUWHcZjpmQ", "pano": false, "user_key": "-uS--wGRrzA9yPvonZ_W4A", "username": "teamwork"}, "geometry": {"type": "Point", "coordinates": [19.106208123504, 47.486997279663996]}}, {"type": "Feature", "properties": {"ca": 117.60700705250008, "camera_make": "", "camera_model": "", "captured_at": "2018-08-02T10:34:13.327Z", "key": "70GaO38T8qJVJnpSvl3dow", "pano": false, "user_key": "-uS--wGRrzA9yPvonZ_W4A", "username": "teamwork"}, "geometry": {"type": "Point", "coordinates": [19.106184591016, 47.487005595655994]}}, {"type": "Feature", "properties": {"ca": 117.60700705250008, "camera_make": "", "camera_model": "", "captured_at": "2018-08-02T10:34:13.150Z", "key": "dETm3V2OfSbwfqadA2P3Sg", "pano": false, "user_key": "-uS--wGRrzA9yPvonZ_W4A", "username": "teamwork"}, "geometry": {"type": "Point", "coordinates": [19.106161058528002, 47.487013911648]}}, {"type": "Feature", "properties": {"ca": 116.25587413863622, "camera_make": "", "camera_model": "", "captured_at": "2018-08-02T10:34:12.975Z", "key": "KaFW_U9fTjtBsN_sNKk3XA", "pano": false, "user_key": "-uS--wGRrzA9yPvonZ_W4A", "username": "teamwork"}, "geometry": {"type": "Point", "coordinates": [19.106137483519998, 47.48702217216]}}, {"type": "Feature", "properties": {"ca": 116.25587413863622, "camera_make": "", "camera_model": "", "captured_at": "2018-08-02T10:34:12.810Z", "key": "LYkjuuSvNd6-_AKAbs_xiA", "pano": false, "user_key": "-uS--wGRrzA9yPvonZ_W4A", "username": "teamwork"}, "geometry": {"type": "Point", "coordinates": [19.106113668656, 47.487030110447996]}}, {"type": "Feature", "properties": {"ca": 116.25587413863622, "camera_make": "", "camera_model": "", "captured_at": "2018-08-02T10:34:12.644Z", "key": "P5pWgSBzysk8Dbf8buqFow", "pano": false, "user_key": "-uS--wGRrzA9yPvonZ_W4A", "username": "teamwork"}, "geometry": {"type": "Point", "coordinates": [19.106089853936002, 47.487038048688]}}, {"type": "Feature", "properties": {"ca": 116.25587413863622, "camera_make": "", "camera_model": "", "captured_at": "2018-08-02T10:34:12.479Z", "key": "IKkT5dsvQLTDTJXF1-7SdQ", "pano": false, "user_key": "-uS--wGRrzA9yPvonZ_W4A", "username": "teamwork"}, "geometry": {"type": "Point", "coordinates": [19.106066039071997, 47.487045986976]}}, {"type": "Feature", "properties": {"ca": 116.25587413863622, "camera_make": "", "camera_model": "", "captured_at": "2018-08-02T10:34:12.314Z", "key": "NR4_1HjTnml0-gyNYVrvjQ", "pano": false, "user_key": "-uS--wGRrzA9yPvonZ_W4A", "username": "teamwork"}, "geometry": {"type": "Point", "coordinates": [19.106042224352002, 47.487053925216]}}, {"type": "Feature", "properties": {"ca": 201.0531602819142, "camera_make": "", "camera_model": "", "captured_at": "2018-07-26T13:38:03.437Z", "key": "nlqVnLm72rmmR_hmymCiYA", "pano": false, "user_key": "-uS--wGRrzA9yPvonZ_W4A", "username": "teamwork"}, "geometry": {"type": "Point", "coordinates": [19.107471302285, 47.486530419567]}}, {"type": "Feature", "properties": {"ca": 201.0531602819142, "camera_make": "", "camera_model": "", "captured_at": "2018-07-26T13:38:03.225Z", "key": "gLJ9W9rutYQ8F9YlCdiQOQ", "pano": false, "user_key": "-uS--wGRrzA9yPvonZ_W4A", "username": "teamwork"}, "geometry": {"type": "Point", "coordinates": [19.107480861275, 47.486547200905]}}, {"type": "Feature", "properties": {"ca": 201.0531602819142, "camera_make": "", "camera_model": "", "captured_at": "2018-07-26T13:38:03.012Z", "key": "GqYlQOGvsod2fHtT0tp9Tw", "pano": false, "user_key": "-uS--wGRrzA9yPvonZ_W4A", "username": "teamwork"}, "geometry": {"type": "Point", "coordinates": [19.107490420264998, 47.486563982243]}}, {"type": "Feature", "properties": {"ca": 201.87745473814277, "camera_make": "", "camera_model": "", "captured_at": "2018-07-26T13:38:02.772Z", "key": "V8H59cnw5DlaAyqjj2ht4g", "pano": false, "user_key": "-uS--wGRrzA9yPvonZ_W4A", "username": "teamwork"}, "geometry": {"type": "Point", "coordinates": [19.107500313724, 47.486580674315995]}}, {"type": "Feature", "properties": {"ca": 201.87745473814277, "camera_make": "", "camera_model": "", "captured_at": "2018-07-26T13:38:02.531Z", "key": "wQ5UzOK5ZT03UBI-R4p48w", "pano": false, "user_key": "-uS--wGRrzA9yPvonZ_W4A", "username": "teamwork"}, "geometry": {"type": "Point", "coordinates": [19.107510228671998, 47.486597360448]}}, {"type": "Feature", "properties": {"ca": 201.87745473814277, "camera_make": "", "camera_model": "", "captured_at": "2018-07-26T13:38:02.289Z", "key": "xXD0CA0tEU3P8Fs0drolPw", "pano": false, "user_key": "-uS--wGRrzA9yPvonZ_W4A", "username": "teamwork"}, "geometry": {"type": "Point", "coordinates": [19.107520143661002, 47.486614046649]}}, {"type": "Feature", "properties": {"ca": 201.87745473814277, "camera_make": "", "camera_model": "", "captured_at": "2018-07-26T13:38:02.047Z", "key": "nyo1KLQsNt5waP8JE9__HA", "pano": false, "user_key": "-uS--wGRrzA9yPvonZ_W4A", "username": "teamwork"}, "geometry": {"type": "Point", "coordinates": [19.107530058608997, 47.486630732781]}}, {"type": "Feature", "properties": {"ca": 202.70097292252046, "camera_make": "", "camera_model": "", "captured_at": "2018-07-26T13:38:01.788Z", "key": "VZH4kjuIQfbKuDYBEv500Q", "pano": false, "user_key": "-uS--wGRrzA9yPvonZ_W4A", "username": "teamwork"}, "geometry": {"type": "Point", "coordinates": [19.107540258055, 47.486647339935004]}}, {"type": "Feature", "properties": {"ca": 202.70097292252046, "camera_make": "", "camera_model": "", "captured_at": "2018-07-26T13:38:01.524Z", "key": "BnrDTf9Jn4DnqCnIxuhv0Q", "pano": false, "user_key": "-uS--wGRrzA9yPvonZ_W4A", "username": "teamwork"}, "geometry": {"type": "Point", "coordinates": [19.10755052656, 47.48666392752]}}, {"type": "Feature", "properties": {"ca": 202.70097292252046, "camera_make": "", "camera_model": "", "captured_at": "2018-07-26T13:38:01.261Z", "key": "shSmwv1Jj_fpxTFk9vyd3w", "pano": false, "user_key": "-uS--wGRrzA9yPvonZ_W4A", "username": "teamwork"}, "geometry": {"type": "Point", "coordinates": [19.107560795104, 47.486680515168004]}}, {"type": "Feature", "properties": {"ca": 198.409387808264, "camera_make": "", "camera_model": "", "captured_at": "2018-07-26T13:38:00.998Z", "key": "BPzSsHeGhS2appGJNAPxKw", "pano": false, "user_key": "-uS--wGRrzA9yPvonZ_W4A", "username": "teamwork"}, "geometry": {"type": "Point", "coordinates": [19.107571052206, 47.486697105994004]}}, {"type": "Feature", "properties": {"ca": 198.409387808264, "camera_make": "", "camera_model": "", "captured_at": "2018-07-26T13:38:00.743Z", "key": "Fo5UuuMZqpv36plXrSKPtQ", "pano": false, "user_key": "-uS--wGRrzA9yPvonZ_W4A", "username": "teamwork"}, "geometry": {"type": "Point", "coordinates": [19.107579456382, 47.486714169018]}}, {"type": "Feature", "properties": {"ca": 198.409387808264, "camera_make": "", "camera_model": "", "captured_at": "2018-07-26T13:38:00.489Z", "key": "0orbdokJaIeb4pAdDmRWyw", "pano": false, "user_key": "-uS--wGRrzA9yPvonZ_W4A", "username": "teamwork"}, "geometry": {"type": "Point", "coordinates": [19.107587860525, 47.486731231975]}}, {"type": "Feature", "properties": {"ca": 198.409387808264, "camera_make": "", "camera_model": "", "captured_at": "2018-07-26T13:38:00.234Z", "key": "FweiBumx2O8DoiQja7plHg", "pano": false, "user_key": "-uS--wGRrzA9yPvonZ_W4A", "username": "teamwork"}, "geometry": {"type": "Point", "coordinates": [19.107596264668, 47.486748294932006]}}, {"type": "Feature", "properties": {"ca": 198.66909687134762, "camera_make": "", "camera_model": "", "captured_at": "2018-07-26T13:37:59.980Z", "key": "RXhvxlqHkMYpVLLlOPCH3Q", "pano": false, "user_key": "-uS--wGRrzA9yPvonZ_W4A", "username": "teamwork"}, "geometry": {"type": "Point", "coordinates": [19.107604677892, 47.486765355784]}}, {"type": "Feature", "properties": {"ca": 198.66909687134762, "camera_make": "", "camera_model": "", "captured_at": "2018-07-26T13:37:59.729Z", "key": "cyxxNU_FUGuDGGsj07jm0g", "pano": false, "user_key": "-uS--wGRrzA9yPvonZ_W4A", "username": "teamwork"}, "geometry": {"type": "Point", "coordinates": [19.107613196354002, 47.48678239270801]}}, {"type": "Feature", "properties": {"ca": 198.66909687134762, "camera_make": "", "camera_model": "", "captured_at": "2018-07-26T13:37:59.478Z", "key": "2Y2evaqcLS1fQWI4ZszJlg", "pano": false, "user_key": "-uS--wGRrzA9yPvonZ_W4A", "username": "teamwork"}, "geometry": {"type": "Point", "coordinates": [19.107621714782, 47.486799429564]}}, {"type": "Feature", "properties": {"ca": 198.66909687134762, "camera_make": "", "camera_model": "", "captured_at": "2018-07-26T13:37:59.228Z", "key": "XIMrprjSVVSAPf2ZxsWoxg", "pano": false, "user_key": "-uS--wGRrzA9yPvonZ_W4A", "username": "teamwork"}, "geometry": {"type": "Point", "coordinates": [19.107630233244002, 47.486816466488]}}, {"type": "Feature", "properties": {"ca": 199.46719236624574, "camera_make": "", "camera_model": "", "captured_at": "2018-07-26T13:37:58.976Z", "key": "dbW4jbNqTrOWrcCMVmTfRg", "pano": false, "user_key": "-uS--wGRrzA9yPvonZ_W4A", "username": "teamwork"}, "geometry": {"type": "Point", "coordinates": [19.107638782680002, 47.4868334963]}}, {"type": "Feature", "properties": {"ca": 199.46719236624574, "camera_make": "", "camera_model": "", "captured_at": "2018-07-26T13:37:58.716Z", "key": "Z73IdEsiiZrJljD6QvkgXg", "pano": false, "user_key": "-uS--wGRrzA9yPvonZ_W4A", "username": "teamwork"}, "geometry": {"type": "Point", "coordinates": [19.10764765124, 47.4868504509]}}, {"type": "Feature", "properties": {"ca": 199.46719236624574, "camera_make": "", "camera_model": "", "captured_at": "2018-07-26T13:37:58.194Z", "key": "wOGyk-EHYcQ4L8FdsqQw7Q", "pano": false, "user_key": "-uS--wGRrzA9yPvonZ_W4A", "username": "teamwork"}, "geometry": {"type": "Point", "coordinates": [19.10766538836, 47.4868843601]}}, {"type": "Feature", "properties": {"ca": 201.27695141604363, "camera_make": "", "camera_model": "", "captured_at": "2018-07-26T13:37:57.927Z", "key": "q2VpR8nwzDSRIBa_ZJc4Jg", "pano": false, "user_key": "-uS--wGRrzA9yPvonZ_W4A", "username": "teamwork"}, "geometry": {"type": "Point", "coordinates": [19.107674458234, 47.486901265759]}}, {"type": "Feature", "properties": {"ca": 201.27695141604363, "camera_make": "", "camera_model": "", "captured_at": "2018-07-26T13:37:57.643Z", "key": "XUEqDVYtYhnR17-0zD3YSw", "pano": false, "user_key": "-uS--wGRrzA9yPvonZ_W4A", "username": "teamwork"}, "geometry": {"type": "Point", "coordinates": [19.107684114132, 47.486918021582]}}, {"type": "Feature", "properties": {"ca": 201.27695141604363, "camera_make": "", "camera_model": "", "captured_at": "2018-07-26T13:37:57.359Z", "key": "_Usg6CiI0k4G-Q8fzllhEA", "pano": false, "user_key": "-uS--wGRrzA9yPvonZ_W4A", "username": "teamwork"}, "geometry": {"type": "Point", "coordinates": [19.10769377003, 47.486934777405]}}, {"type": "Feature", "properties": {"ca": 201.27695141604363, "camera_make": "", "camera_model": "", "captured_at": "2018-07-26T13:37:57.075Z", "key": "wnoka35gTmIYYodkWoSSWA", "pano": false, "user_key": "-uS--wGRrzA9yPvonZ_W4A", "username": "teamwork"}, "geometry": {"type": "Point", "coordinates": [19.107703425928, 47.486951533227995]}}, {"type": "Feature", "properties": {"ca": 200.9320813978951, "camera_make": "", "camera_model": "", "captured_at": "2018-07-26T13:37:56.767Z", "key": "QjtWzR41zUd_hjLduC4_zQ", "pano": false, "user_key": "-uS--wGRrzA9yPvonZ_W4A", "username": "teamwork"}, "geometry": {"type": "Point", "coordinates": [19.10771297236, 47.486968317836]}}, {"type": "Feature", "properties": {"ca": 200.9320813978951, "camera_make": "", "camera_model": "", "captured_at": "2018-07-26T13:37:56.450Z", "key": "7jmlU_4CsX6JUBv-NUoJmw", "pano": false, "user_key": "-uS--wGRrzA9yPvonZ_W4A", "username": "teamwork"}, "geometry": {"type": "Point", "coordinates": [19.107722478969997, 47.486985112846995]}}, {"type": "Feature", "properties": {"ca": 200.9320813978951, "camera_make": "", "camera_model": "", "captured_at": "2018-07-26T13:37:56.133Z", "key": "TvSAvydo0x36JKyVA0_1vA", "pano": false, "user_key": "-uS--wGRrzA9yPvonZ_W4A", "username": "teamwork"}, "geometry": {"type": "Point", "coordinates": [19.10773198558, 47.487001907857994]}}, {"type": "Feature", "properties": {"ca": 199.6467632309582, "camera_make": "", "camera_model": "", "captured_at": "2018-07-26T13:37:55.815Z", "key": "QjGJ9CiOC3K487p9464bCQ", "pano": false, "user_key": "-uS--wGRrzA9yPvonZ_W4A", "username": "teamwork"}, "geometry": {"type": "Point", "coordinates": [19.107741169528, 47.487018785178]}}, {"type": "Feature", "properties": {"ca": 199.6467632309582, "camera_make": "", "camera_model": "", "captured_at": "2018-07-26T13:37:55.495Z", "key": "ELzzYkL0089cboq_9Tf7uA", "pano": false, "user_key": "-uS--wGRrzA9yPvonZ_W4A", "username": "teamwork"}, "geometry": {"type": "Point", "coordinates": [19.107750116648, 47.487035720798005]}}, {"type": "Feature", "properties": {"ca": 199.6467632309582, "camera_make": "", "camera_model": "", "captured_at": "2018-07-26T13:37:55.176Z", "key": "OYsuaoWrnM9HJNPk-PK-xA", "pano": false, "user_key": "-uS--wGRrzA9yPvonZ_W4A", "username": "teamwork"}, "geometry": {"type": "Point", "coordinates": [19.107759063796, 47.48705265647099]}}, {"type": "Feature", "properties": {"ca": 187.7900390625, "camera_make": "SAMSUNG", "camera_model": "SM-N9005", "captured_at": "2018-06-29T09:20:06.279Z", "key": "N92rnicwvJVtwvQLYPN9WA", "pano": false, "user_key": "i1FGvYWQoDeMVAlkvDwvUA", "username": "vst"}, "geometry": {"type": "Point", "coordinates": [19.107381516305374, 47.48661753355325]}}, {"type": "Feature", "properties": {"ca": 201.70602416992188, "camera_make": "SAMSUNG", "camera_model": "SM-N9005", "captured_at": "2018-06-29T09:20:04.953Z", "key": "ZvTA6rCBfLERh2R-rb7Vbg", "pano": false, "user_key": "i1FGvYWQoDeMVAlkvDwvUA", "username": "vst"}, "geometry": {"type": "Point", "coordinates": [19.107431979979676, 47.48672877632114]}}, {"type": "Feature", "properties": {"ca": 202.45616149902344, "camera_make": "SAMSUNG", "camera_model": "SM-N9005", "captured_at": "2018-06-29T09:20:03.919Z", "key": "FEEFWWrb7YZtibXJdXvYsg", "pano": false, "user_key": "i1FGvYWQoDeMVAlkvDwvUA", "username": "vst"}, "geometry": {"type": "Point", "coordinates": [19.107480685218256, 47.48680886775794]}}, {"type": "Feature", "properties": {"ca": 206.75787353515625, "camera_make": "SAMSUNG", "camera_model": "SM-N9005", "captured_at": "2018-06-29T09:20:02.473Z", "key": "njjrmMvKD0y2eF1SkJ5m9Q", "pano": false, "user_key": "i1FGvYWQoDeMVAlkvDwvUA", "username": "vst"}, "geometry": {"type": "Point", "coordinates": [19.10755471818182, 47.486920192094864]}}, {"type": "Feature", "properties": {"ca": 200.1215362548828, "camera_make": "SAMSUNG", "camera_model": "SM-N9005", "captured_at": "2018-06-29T09:20:01.230Z", "key": "CJmz_-go1Nv4z9ep9B-KXg", "pano": false, "user_key": "i1FGvYWQoDeMVAlkvDwvUA", "username": "vst"}, "geometry": {"type": "Point", "coordinates": [19.1076145878607, 47.487014175820896]}}, {"type": "Feature", "properties": {"ca": 0, "camera_make": "LG Electronics", "camera_model": "LG-R105", "captured_at": "2018-06-23T14:50:02.572Z", "key": "9m9gQZ7AVXjwwr4MhQ-i4w", "pano": true, "user_key": "zp30vjlEfGf9QDbyOUyBIQ", "username": "kami911"}, "geometry": {"type": "Point", "coordinates": [19.106260000000002, 47.486966799986995]}}, {"type": "Feature", "properties": {"ca": 0, "camera_make": "LG Electronics", "camera_model": "LG-R105", "captured_at": "2018-06-23T14:50:02.572Z", "key": "hFxMrKgS2wKY8FUaGwu7FA", "pano": true, "user_key": "zp30vjlEfGf9QDbyOUyBIQ", "username": "kami911"}, "geometry": {"type": "Point", "coordinates": [19.106260000000002, 47.486966799986995]}}, {"type": "Feature", "properties": {"ca": 0, "camera_make": "LG Electronics", "camera_model": "LG-R105", "captured_at": "2018-06-23T14:50:00.572Z", "key": "lsXYiodnwrP2pH_3mCpVqQ", "pano": true, "user_key": "zp30vjlEfGf9QDbyOUyBIQ", "username": "kami911"}, "geometry": {"type": "Point", "coordinates": [19.10652106666667, 47.48688819999637]}}, {"type": "Feature", "properties": {"ca": 0, "camera_make": "LG Electronics", "camera_model": "LG-R105", "captured_at": "2018-06-23T14:50:00.572Z", "key": "C3EyDlMa7k2JZudrYXk5ng", "pano": true, "user_key": "zp30vjlEfGf9QDbyOUyBIQ", "username": "kami911"}, "geometry": {"type": "Point", "coordinates": [19.10652106666667, 47.48688819999637]}}, {"type": "Feature", "properties": {"ca": 0, "camera_make": "LG Electronics", "camera_model": "LG-R105", "captured_at": "2018-06-23T14:49:58.577Z", "key": "1dAFBOBM9LHUaST9QeiHdQ", "pano": true, "user_key": "zp30vjlEfGf9QDbyOUyBIQ", "username": "kami911"}, "geometry": {"type": "Point", "coordinates": [19.106776733349403, 47.486801666666665]}}, {"type": "Feature", "properties": {"ca": 0, "camera_make": "LG Electronics", "camera_model": "LG-R105", "captured_at": "2018-06-23T14:49:58.577Z", "key": "gNQydpNYNCNxQNNjB95www", "pano": true, "user_key": "zp30vjlEfGf9QDbyOUyBIQ", "username": "kami911"}, "geometry": {"type": "Point", "coordinates": [19.106776733349403, 47.486801666666665]}}, {"type": "Feature", "properties": {"ca": 0, "camera_make": "LG Electronics", "camera_model": "LG-R105", "captured_at": "2018-06-23T14:49:56.572Z", "key": "FUSUsMhuNPcxGkkCcj2VIg", "pano": true, "user_key": "zp30vjlEfGf9QDbyOUyBIQ", "username": "kami911"}, "geometry": {"type": "Point", "coordinates": [19.107027000000002, 47.4867072]}}, {"type": "Feature", "properties": {"ca": 0, "camera_make": "LG Electronics", "camera_model": "LG-R105", "captured_at": "2018-06-23T14:49:56.572Z", "key": "v4BIHSIUVfbR8tl9cm5_PA", "pano": true, "user_key": "zp30vjlEfGf9QDbyOUyBIQ", "username": "kami911"}, "geometry": {"type": "Point", "coordinates": [19.107027000000002, 47.4867072]}}, {"type": "Feature", "properties": {"ca": 0, "camera_make": "LG Electronics", "camera_model": "LG-R105", "captured_at": "2018-06-23T14:49:54.578Z", "key": "nROf3TlbEo8kzPPgUPFo7A", "pano": true, "user_key": "zp30vjlEfGf9QDbyOUyBIQ", "username": "kami911"}, "geometry": {"type": "Point", "coordinates": [19.107408000000003, 47.48660059998168]}}, {"type": "Feature", "properties": {"ca": 0, "camera_make": "LG Electronics", "camera_model": "LG-R105", "captured_at": "2018-06-23T14:49:54.578Z", "key": "PAgkn4-e3XJwGN4lhGm5Kw", "pano": true, "user_key": "zp30vjlEfGf9QDbyOUyBIQ", "username": "kami911"}, "geometry": {"type": "Point", "coordinates": [19.107408000000003, 47.48660059998168]}}, {"type": "Feature", "properties": {"ca": 0, "camera_make": "LG Electronics", "camera_model": "LG-R105", "captured_at": "2018-06-23T14:49:52.584Z", "key": "fsXUGttB_Fd245WzhqJyDw", "pano": true, "user_key": "zp30vjlEfGf9QDbyOUyBIQ", "username": "kami911"}, "geometry": {"type": "Point", "coordinates": [19.107575799981344, 47.486563733333334]}}, {"type": "Feature", "properties": {"ca": 0, "camera_make": "LG Electronics", "camera_model": "LG-R105", "captured_at": "2018-06-23T14:49:52.584Z", "key": "HMLsv83yZmmL32Hxg5tYEg", "pano": true, "user_key": "zp30vjlEfGf9QDbyOUyBIQ", "username": "kami911"}, "geometry": {"type": "Point", "coordinates": [19.107575799981344, 47.486563733333334]}}, {"type": "Feature", "properties": {"ca": 17.37835693359375, "camera_make": "SAMSUNG", "camera_model": "SM-N9005", "captured_at": "2018-05-02T09:48:48.726Z", "key": "UocnRsGxAxPbKIEYWAZFHw", "pano": false, "user_key": "i1FGvYWQoDeMVAlkvDwvUA", "username": "vst"}, "geometry": {"type": "Point", "coordinates": [19.10799964141313, 47.48669842286557]}}, {"type": "Feature", "properties": {"ca": 23.100067138671875, "camera_make": "SAMSUNG", "camera_model": "SM-N9005", "captured_at": "2018-05-02T09:48:47.582Z", "key": "9gNhRY3XgUWQoRBj5om0ew", "pano": false, "user_key": "i1FGvYWQoDeMVAlkvDwvUA", "username": "vst"}, "geometry": {"type": "Point", "coordinates": [19.107906167731926, 47.486526423505154]}}, {"type": "Feature", "properties": {"ca": 195.65484619140625, "camera_make": "SAMSUNG", "camera_model": "SM-N9005", "captured_at": "2018-04-24T09:43:40.521Z", "key": "bLMQktZmKGUcgH-MKHPVGQ", "pano": false, "user_key": "i1FGvYWQoDeMVAlkvDwvUA", "username": "vst"}, "geometry": {"type": "Point", "coordinates": [19.107555232092523, 47.486563994567405]}}, {"type": "Feature", "properties": {"ca": 195.51931762695312, "camera_make": "SAMSUNG", "camera_model": "SM-N9005", "captured_at": "2018-04-24T09:43:39.440Z", "key": "NdcF--wqdxnNbyQK6uEGWA", "pano": false, "user_key": "i1FGvYWQoDeMVAlkvDwvUA", "username": "vst"}, "geometry": {"type": "Point", "coordinates": [19.10759805600003, 47.48666836079997]}}, {"type": "Feature", "properties": {"ca": 203.99563598632812, "camera_make": "SAMSUNG", "camera_model": "SM-N9005", "captured_at": "2018-04-24T09:43:38.356Z", "key": "KUFeYxJlnkr0WRFNXljoAw", "pano": false, "user_key": "i1FGvYWQoDeMVAlkvDwvUA", "username": "vst"}, "geometry": {"type": "Point", "coordinates": [19.107655717693888, 47.48675960417495]}}, {"type": "Feature", "properties": {"ca": 204.04995727539062, "camera_make": "SAMSUNG", "camera_model": "SM-N9005", "captured_at": "2018-04-24T09:43:36.897Z", "key": "JzpK5sq0c4doFb4C5G00-w", "pano": false, "user_key": "i1FGvYWQoDeMVAlkvDwvUA", "username": "vst"}, "geometry": {"type": "Point", "coordinates": [19.10772802058227, 47.48688364497991]}}, {"type": "Feature", "properties": {"ca": 202.79855346679688, "camera_make": "SAMSUNG", "camera_model": "SM-N9005", "captured_at": "2018-04-24T09:43:35.556Z", "key": "XGg1Z8BVxq_qn23qM60r_A", "pano": false, "user_key": "i1FGvYWQoDeMVAlkvDwvUA", "username": "vst"}, "geometry": {"type": "Point", "coordinates": [19.107798986426587, 47.486995922991696]}}, {"type": "Feature", "properties": {"ca": 19.80682373046875, "camera_make": "samsung", "camera_model": "SM-J320FN", "captured_at": "2018-04-05T13:42:55.328Z", "key": "PVYCiXppb5FoiKOwAF27Nw", "pano": false, "user_key": "i1FGvYWQoDeMVAlkvDwvUA", "username": "vst"}, "geometry": {"type": "Point", "coordinates": [19.108003961764666, 47.48661382426474]}}, {"type": "Feature", "properties": {"ca": 20.143280029296875, "camera_make": "samsung", "camera_model": "SM-J320FN", "captured_at": "2018-04-05T13:42:54.208Z", "key": "BzIA4qyA5TyXownQY9X1Hw", "pano": false, "user_key": "i1FGvYWQoDeMVAlkvDwvUA", "username": "vst"}, "geometry": {"type": "Point", "coordinates": [19.107957787781288, 47.48652731061094]}}, {"type": "Feature", "properties": {"ca": 112.38047553994431, "camera_make": "none", "camera_model": "none", "captured_at": "2018-03-30T11:26:40.572Z", "key": "J1FwC9bNdmiS9z8K2jJb2w", "pano": false, "user_key": "-tUIOh7mZ9oUczk7LaMqFQ", "username": "andreas2"}, "geometry": {"type": "Point", "coordinates": [19.107413810819935, 47.48652368742398]}}, {"type": "Feature", "properties": {"ca": 112.38047553994431, "camera_make": "none", "camera_model": "none", "captured_at": "2018-03-30T11:26:40.358Z", "key": "8DrE9eaj2hr3ayYqIh8IEg", "pano": false, "user_key": "-tUIOh7mZ9oUczk7LaMqFQ", "username": "andreas2"}, "geometry": {"type": "Point", "coordinates": [19.10738926062004, 47.48653051878398]}}, {"type": "Feature", "properties": {"ca": 112.38047553994431, "camera_make": "none", "camera_model": "none", "captured_at": "2018-03-30T11:26:40.145Z", "key": "gx1xU7iVJipbLy-4Eyuldw", "pano": false, "user_key": "-tUIOh7mZ9oUczk7LaMqFQ", "username": "andreas2"}, "geometry": {"type": "Point", "coordinates": [19.10736471042003, 47.486537350143976]}}, {"type": "Feature", "properties": {"ca": 111.4350452704341, "camera_make": "none", "camera_model": "none", "captured_at": "2018-03-30T11:26:39.919Z", "key": "_xicZ2ZpHwKpKnznxwi3rQ", "pano": false, "user_key": "-tUIOh7mZ9oUczk7LaMqFQ", "username": "andreas2"}, "geometry": {"type": "Point", "coordinates": [19.107340107570053, 47.48654409390997]}}, {"type": "Feature", "properties": {"ca": 111.4350452704341, "camera_make": "none", "camera_model": "none", "captured_at": "2018-03-30T11:26:39.667Z", "key": "m8Mv1zW6vVesZU2qQ71nag", "pano": false, "user_key": "-tUIOh7mZ9oUczk7LaMqFQ", "username": "andreas2"}, "geometry": {"type": "Point", "coordinates": [19.107315394713964, 47.486550650382014]}}, {"type": "Feature", "properties": {"ca": 111.4350452704341, "camera_make": "none", "camera_model": "none", "captured_at": "2018-03-30T11:26:39.415Z", "key": "alvtRQI0wOfjmU7rzyJb4Q", "pano": false, "user_key": "-tUIOh7mZ9oUczk7LaMqFQ", "username": "andreas2"}, "geometry": {"type": "Point", "coordinates": [19.107290681955988, 47.486557206828024]}}, {"type": "Feature", "properties": {"ca": 111.4350452704341, "camera_make": "none", "camera_model": "none", "captured_at": "2018-03-30T11:26:39.162Z", "key": "ApgRM0eARiocuBS92MYOMQ", "pano": false, "user_key": "-tUIOh7mZ9oUczk7LaMqFQ", "username": "andreas2"}, "geometry": {"type": "Point", "coordinates": [19.107265969100013, 47.48656376330001]}}, {"type": "Feature", "properties": {"ca": 110.08237409527095, "camera_make": "none", "camera_model": "none", "captured_at": "2018-03-30T11:26:38.896Z", "key": "uJfqWoE-0w8Yc4DLw49z2w", "pano": false, "user_key": "-tUIOh7mZ9oUczk7LaMqFQ", "username": "andreas2"}, "geometry": {"type": "Point", "coordinates": [19.10724117657503, 47.486570179905016]}}, {"type": "Feature", "properties": {"ca": 110.08237409527095, "camera_make": "none", "camera_model": "none", "captured_at": "2018-03-30T11:26:38.601Z", "key": "GznZT_J6ufGhjB2jkYB2yA", "pano": false, "user_key": "-tUIOh7mZ9oUczk7LaMqFQ", "username": "andreas2"}, "geometry": {"type": "Point", "coordinates": [19.107216242759932, 47.48657634002399]}}, {"type": "Feature", "properties": {"ca": 110.08237409527095, "camera_make": "none", "camera_model": "none", "captured_at": "2018-03-30T11:26:38.309Z", "key": "drc8WvRLK6cHCX_zL674cw", "pano": false, "user_key": "-tUIOh7mZ9oUczk7LaMqFQ", "username": "andreas2"}, "geometry": {"type": "Point", "coordinates": [19.107191309029986, 47.48658250012204]}}, {"type": "Feature", "properties": {"ca": 110.08237409527095, "camera_make": "none", "camera_model": "none", "captured_at": "2018-03-30T11:26:38.016Z", "key": "SNVUk0MSdJvgp7ZWJOeKVw", "pano": false, "user_key": "-tUIOh7mZ9oUczk7LaMqFQ", "username": "andreas2"}, "geometry": {"type": "Point", "coordinates": [19.107166375215, 47.48658866024101]}}, {"type": "Feature", "properties": {"ca": 108.20324559158877, "camera_make": "none", "camera_model": "none", "captured_at": "2018-03-30T11:26:37.669Z", "key": "xONKmofWYblYPVOCVZ2RSQ", "pano": false, "user_key": "-tUIOh7mZ9oUczk7LaMqFQ", "username": "andreas2"}, "geometry": {"type": "Point", "coordinates": [19.107141172464026, 47.48659429500799]}}, {"type": "Feature", "properties": {"ca": 108.20324559158877, "camera_make": "none", "camera_model": "none", "captured_at": "2018-03-30T11:26:37.318Z", "key": "_SAn9mlM7FKfwDtkUiimHA", "pano": false, "user_key": "-tUIOh7mZ9oUczk7LaMqFQ", "username": "andreas2"}, "geometry": {"type": "Point", "coordinates": [19.107115954751976, 47.48659989894401]}}, {"type": "Feature", "properties": {"ca": 135.6928839781874, "camera_make": "none", "camera_model": "none", "captured_at": "2018-03-30T11:26:34.431Z", "key": "gqXeYNMazcSPRm6H_sN93A", "pano": false, "user_key": "-tUIOh7mZ9oUczk7LaMqFQ", "username": "andreas2"}, "geometry": {"type": "Point", "coordinates": [19.107091144670335, 47.486606284459015]}}, {"type": "Feature", "properties": {"ca": 135.6928839781874, "camera_make": "none", "camera_model": "none", "captured_at": "2018-03-30T11:26:08.723Z", "key": "tTJhaRDFaW4Fib3F0YqP_w", "pano": false, "user_key": "-tUIOh7mZ9oUczk7LaMqFQ", "username": "andreas2"}, "geometry": {"type": "Point", "coordinates": [19.107072578396128, 47.48661913803346]}}, {"type": "Feature", "properties": {"ca": 111.68081551797576, "camera_make": "none", "camera_model": "none", "captured_at": "2018-03-30T11:26:00.471Z", "key": "X0lUZ-7YAHxgMf9AdU14jQ", "pano": false, "user_key": "-tUIOh7mZ9oUczk7LaMqFQ", "username": "andreas2"}, "geometry": {"type": "Point", "coordinates": [19.107049286104484, 47.48662775895701]}}, {"type": "Feature", "properties": {"ca": 111.68081551797576, "camera_make": "none", "camera_model": "none", "captured_at": "2018-03-30T11:25:59.734Z", "key": "D2EYC-4PWCKDPPfnATO2lQ", "pano": false, "user_key": "-tUIOh7mZ9oUczk7LaMqFQ", "username": "andreas2"}, "geometry": {"type": "Point", "coordinates": [19.107024614895522, 47.48663438704301]}}, {"type": "Feature", "properties": {"ca": 112.34551459507338, "camera_make": "none", "camera_model": "none", "captured_at": "2018-03-30T11:25:58.998Z", "key": "ZFzYn0QVpL-2Pgsrp6MUaw", "pano": false, "user_key": "-tUIOh7mZ9oUczk7LaMqFQ", "username": "andreas2"}, "geometry": {"type": "Point", "coordinates": [19.10699994394804, 47.48664101557]}}, {"type": "Feature", "properties": {"ca": 112.34551459507338, "camera_make": "none", "camera_model": "none", "captured_at": "2018-03-30T11:25:58.544Z", "key": "E57sAIeNmoDz8bXt3R0PEA", "pano": false, "user_key": "-tUIOh7mZ9oUczk7LaMqFQ", "username": "andreas2"}, "geometry": {"type": "Point", "coordinates": [19.10697538750196, 47.48664783680499]}}, {"type": "Feature", "properties": {"ca": 112.34551459507338, "camera_make": "none", "camera_model": "none", "captured_at": "2018-03-30T11:25:58.089Z", "key": "lhkoIoerBPaqNZa64m6Jbg", "pano": false, "user_key": "-tUIOh7mZ9oUczk7LaMqFQ", "username": "andreas2"}, "geometry": {"type": "Point", "coordinates": [19.106950831109998, 47.48665465802503]}}, {"type": "Feature", "properties": {"ca": 110.86499834232978, "camera_make": "none", "camera_model": "none", "captured_at": "2018-03-30T11:25:57.698Z", "key": "QNwKk-v0q7wo9tStEFTaSQ", "pano": false, "user_key": "-tUIOh7mZ9oUczk7LaMqFQ", "username": "andreas2"}, "geometry": {"type": "Point", "coordinates": [19.106926071630028, 47.48666113306501]}}, {"type": "Feature", "properties": {"ca": 110.86499834232978, "camera_make": "none", "camera_model": "none", "captured_at": "2018-03-30T11:25:57.321Z", "key": "MUAXGhZVkXaK9IhsI2vvTA", "pano": false, "user_key": "-tUIOh7mZ9oUczk7LaMqFQ", "username": "andreas2"}, "geometry": {"type": "Point", "coordinates": [19.10690126394593, 47.48666752292297]}}, {"type": "Feature", "properties": {"ca": 111.47304589924346, "camera_make": "none", "camera_model": "none", "captured_at": "2018-03-30T11:25:56.955Z", "key": "fzSHG7NQm8psBSdz0Gw9MQ", "pano": false, "user_key": "-tUIOh7mZ9oUczk7LaMqFQ", "username": "andreas2"}, "geometry": {"type": "Point", "coordinates": [19.106876470596035, 47.48667393819596]}}, {"type": "Feature", "properties": {"ca": 111.47304589924346, "camera_make": "none", "camera_model": "none", "captured_at": "2018-03-30T11:25:56.642Z", "key": "gJ5SSLP2_XPXtyNUXDaxCA", "pano": false, "user_key": "-tUIOh7mZ9oUczk7LaMqFQ", "username": "andreas2"}, "geometry": {"type": "Point", "coordinates": [19.106851764135968, 47.48668050573599]}}, {"type": "Feature", "properties": {"ca": 111.47304589924346, "camera_make": "none", "camera_model": "none", "captured_at": "2018-03-30T11:25:56.329Z", "key": "LU1HV5iaNZJW5PEhZISo9g", "pano": false, "user_key": "-tUIOh7mZ9oUczk7LaMqFQ", "username": "andreas2"}, "geometry": {"type": "Point", "coordinates": [19.106827057676014, 47.486687073276016]}}, {"type": "Feature", "properties": {"ca": 111.47304589924346, "camera_make": "none", "camera_model": "none", "captured_at": "2018-03-30T11:25:56.017Z", "key": "elngVqMpb_pIivPP7kFLaw", "pano": false, "user_key": "-tUIOh7mZ9oUczk7LaMqFQ", "username": "andreas2"}, "geometry": {"type": "Point", "coordinates": [19.106802351215947, 47.486693640815986]}}, {"type": "Feature", "properties": {"ca": 110.92799441728187, "camera_make": "none", "camera_model": "none", "captured_at": "2018-03-30T11:25:55.736Z", "key": "0qOx09SIO3bsZuNkA58zjw", "pano": false, "user_key": "-tUIOh7mZ9oUczk7LaMqFQ", "username": "andreas2"}, "geometry": {"type": "Point", "coordinates": [19.10677755882398, 47.48670005783197]}}, {"type": "Feature", "properties": {"ca": 110.92799441728187, "camera_make": "none", "camera_model": "none", "captured_at": "2018-03-30T11:25:55.457Z", "key": "CVHGE1-OGUb8CE5AcJRP5Q", "pano": false, "user_key": "-tUIOh7mZ9oUczk7LaMqFQ", "username": "andreas2"}, "geometry": {"type": "Point", "coordinates": [19.10675276146594, 47.486706466138]}}, {"type": "Feature", "properties": {"ca": 110.92799441728187, "camera_make": "none", "camera_model": "none", "captured_at": "2018-03-30T11:25:55.179Z", "key": "lNdQx-KBM0qUPqXbjzKKig", "pano": false, "user_key": "-tUIOh7mZ9oUczk7LaMqFQ", "username": "andreas2"}, "geometry": {"type": "Point", "coordinates": [19.106727964108018, 47.48671287444398]}}, {"type": "Feature", "properties": {"ca": 111.77912163083568, "camera_make": "none", "camera_model": "none", "captured_at": "2018-03-30T11:25:54.912Z", "key": "Q5DRvkIZ1xR80xRo58Fgpw", "pano": false, "user_key": "-tUIOh7mZ9oUczk7LaMqFQ", "username": "andreas2"}, "geometry": {"type": "Point", "coordinates": [19.10670321709995, 47.486719371383]}}, {"type": "Feature", "properties": {"ca": 111.77912163083568, "camera_make": "none", "camera_model": "none", "captured_at": "2018-03-30T11:25:54.665Z", "key": "YA_TQWynUxISAsoxQ-DK7g", "pano": false, "user_key": "-tUIOh7mZ9oUczk7LaMqFQ", "username": "andreas2"}, "geometry": {"type": "Point", "coordinates": [19.106678562599996, 47.48672602809802]}}, {"type": "Feature", "properties": {"ca": 111.77912163083568, "camera_make": "none", "camera_model": "none", "captured_at": "2018-03-30T11:25:54.419Z", "key": "bhZ_IeBTUgPUYiZfiZO3LQ", "pano": false, "user_key": "-tUIOh7mZ9oUczk7LaMqFQ", "username": "andreas2"}, "geometry": {"type": "Point", "coordinates": [19.106653908100043, 47.48673268481298]}}, {"type": "Feature", "properties": {"ca": 111.77912163083568, "camera_make": "none", "camera_model": "none", "captured_at": "2018-03-30T11:25:54.172Z", "key": "G3F6Deepn4M6CPDKHHA7Mg", "pano": false, "user_key": "-tUIOh7mZ9oUczk7LaMqFQ", "username": "andreas2"}, "geometry": {"type": "Point", "coordinates": [19.106629253599976, 47.48673934152799]}}, {"type": "Feature", "properties": {"ca": 113.01387426740558, "camera_make": "none", "camera_model": "none", "captured_at": "2018-03-30T11:25:53.932Z", "key": "yBF2lw77kHD0zSAcXqwhDg", "pano": false, "user_key": "-tUIOh7mZ9oUczk7LaMqFQ", "username": "andreas2"}, "geometry": {"type": "Point", "coordinates": [19.106604663019993, 47.48674610598499]}}, {"type": "Feature", "properties": {"ca": 113.01387426740558, "camera_make": "none", "camera_model": "none", "captured_at": "2018-03-30T11:25:53.705Z", "key": "KfzV4qi8uTPRbSMQLROcNQ", "pano": false, "user_key": "-tUIOh7mZ9oUczk7LaMqFQ", "username": "andreas2"}, "geometry": {"type": "Point", "coordinates": [19.10658022531993, 47.48675312051]}}, {"type": "Feature", "properties": {"ca": 113.01387426740558, "camera_make": "none", "camera_model": "none", "captured_at": "2018-03-30T11:25:53.479Z", "key": "Ba0EH_B_5c3VuQzyINMU2g", "pano": false, "user_key": "-tUIOh7mZ9oUczk7LaMqFQ", "username": "andreas2"}, "geometry": {"type": "Point", "coordinates": [19.106555787727984, 47.48676013500403]}}, {"type": "Feature", "properties": {"ca": 113.01387426740558, "camera_make": "none", "camera_model": "none", "captured_at": "2018-03-30T11:25:53.253Z", "key": "B1TEcKkPm2VRNYaEJSQ7PQ", "pano": false, "user_key": "-tUIOh7mZ9oUczk7LaMqFQ", "username": "andreas2"}, "geometry": {"type": "Point", "coordinates": [19.106531350136038, 47.48676714949801]}}, {"type": "Feature", "properties": {"ca": 113.01387426740558, "camera_make": "none", "camera_model": "none", "captured_at": "2018-03-30T11:25:53.025Z", "key": "yrwjWoIrBbvgtLoycwDowQ", "pano": false, "user_key": "-tUIOh7mZ9oUczk7LaMqFQ", "username": "andreas2"}, "geometry": {"type": "Point", "coordinates": [19.106506912435975, 47.48677416402302]}}, {"type": "Feature", "properties": {"ca": 114.29765659315262, "camera_make": "none", "camera_model": "none", "captured_at": "2018-03-30T11:25:52.819Z", "key": "aPJXylIOA_6hUnP-V3QxHA", "pano": false, "user_key": "-tUIOh7mZ9oUczk7LaMqFQ", "username": "andreas2"}, "geometry": {"type": "Point", "coordinates": [19.106482683299987, 47.48678150340004]}}, {"type": "Feature", "properties": {"ca": 114.29765659315262, "camera_make": "none", "camera_model": "none", "captured_at": "2018-03-30T11:25:52.614Z", "key": "yGBJ3hESxrjjRYZAa7pn8Q", "pano": false, "user_key": "-tUIOh7mZ9oUczk7LaMqFQ", "username": "andreas2"}, "geometry": {"type": "Point", "coordinates": [19.106458483033975, 47.486788886532]}}, {"type": "Feature", "properties": {"ca": 114.29765659315262, "camera_make": "none", "camera_model": "none", "captured_at": "2018-03-30T11:25:52.409Z", "key": "j4Ux2bONUUmpmQIwKXscMw", "pano": false, "user_key": "-tUIOh7mZ9oUczk7LaMqFQ", "username": "andreas2"}, "geometry": {"type": "Point", "coordinates": [19.10643428288597, 47.48679626962803]}}, {"type": "Feature", "properties": {"ca": 114.29765659315262, "camera_make": "none", "camera_model": "none", "captured_at": "2018-03-30T11:25:52.204Z", "key": "X2Uqka_Phg4IYe_uKU-BaQ", "pano": false, "user_key": "-tUIOh7mZ9oUczk7LaMqFQ", "username": "andreas2"}, "geometry": {"type": "Point", "coordinates": [19.106410082737966, 47.48680365272401]}}, {"type": "Feature", "properties": {"ca": 114.48105630204896, "camera_make": "none", "camera_model": "none", "captured_at": "2018-03-30T11:25:51.999Z", "key": "a2Lb6xEJ-JMZjGVI399ZIA", "pano": false, "user_key": "-tUIOh7mZ9oUczk7LaMqFQ", "username": "andreas2"}, "geometry": {"type": "Point", "coordinates": [19.106385882740028, 47.486811036079985]}}, {"type": "Feature", "properties": {"ca": 114.48105630204896, "camera_make": "none", "camera_model": "none", "captured_at": "2018-03-30T11:25:51.813Z", "key": "ZaN8wRRZJfL9CCNoqJ2aaQ", "pano": false, "user_key": "-tUIOh7mZ9oUczk7LaMqFQ", "username": "andreas2"}, "geometry": {"type": "Point", "coordinates": [19.10636171742999, 47.486818471560014]}}, {"type": "Feature", "properties": {"ca": 114.48105630204896, "camera_make": "none", "camera_model": "none", "captured_at": "2018-03-30T11:25:51.627Z", "key": "tUs4AQ5_Bk9hYw461YqX2w", "pano": false, "user_key": "-tUIOh7mZ9oUczk7LaMqFQ", "username": "andreas2"}, "geometry": {"type": "Point", "coordinates": [19.10633755225001, 47.486825907000025]}}, {"type": "Feature", "properties": {"ca": 114.48105630204896, "camera_make": "none", "camera_model": "none", "captured_at": "2018-03-30T11:25:51.441Z", "key": "m9Y7FefMxkc5ms8HZtNtdA", "pano": false, "user_key": "-tUIOh7mZ9oUczk7LaMqFQ", "username": "andreas2"}, "geometry": {"type": "Point", "coordinates": [19.106313386939973, 47.48683334248]}}, {"type": "Feature", "properties": {"ca": 114.48105630204896, "camera_make": "none", "camera_model": "none", "captured_at": "2018-03-30T11:25:51.255Z", "key": "sWZkVzlhFUAFG1ZgdNJYEg", "pano": false, "user_key": "-tUIOh7mZ9oUczk7LaMqFQ", "username": "andreas2"}, "geometry": {"type": "Point", "coordinates": [19.10628922163005, 47.48684077795997]}}, {"type": "Feature", "properties": {"ca": 114.48105630204896, "camera_make": "none", "camera_model": "none", "captured_at": "2018-03-30T11:25:51.069Z", "key": "ef2IHjDplMO5c7PYXoUUQw", "pano": false, "user_key": "-tUIOh7mZ9oUczk7LaMqFQ", "username": "andreas2"}, "geometry": {"type": "Point", "coordinates": [19.106265056320012, 47.48684821344]}}, {"type": "Feature", "properties": {"ca": 114.81779324065974, "camera_make": "none", "camera_model": "none", "captured_at": "2018-03-30T11:25:50.895Z", "key": "dB9l7VnVYZTYGdvRv75aCA", "pano": false, "user_key": "-tUIOh7mZ9oUczk7LaMqFQ", "username": "andreas2"}, "geometry": {"type": "Point", "coordinates": [19.106240931408024, 47.48685570893497]}}, {"type": "Feature", "properties": {"ca": 114.81779324065974, "camera_make": "none", "camera_model": "none", "captured_at": "2018-03-30T11:25:50.727Z", "key": "Qw3DMtHk6_hCEpWoEL3Y1Q", "pano": false, "user_key": "-tUIOh7mZ9oUczk7LaMqFQ", "username": "andreas2"}, "geometry": {"type": "Point", "coordinates": [19.106216830847984, 47.48686324035998]}}, {"type": "Feature", "properties": {"ca": 114.81779324065974, "camera_make": "none", "camera_model": "none", "captured_at": "2018-03-30T11:25:50.560Z", "key": "Dy0O466noaxL1stbK_05yg", "pano": false, "user_key": "-tUIOh7mZ9oUczk7LaMqFQ", "username": "andreas2"}, "geometry": {"type": "Point", "coordinates": [19.106192730288058, 47.48687077178499]}}, {"type": "Feature", "properties": {"ca": 114.81779324065974, "camera_make": "none", "camera_model": "none", "captured_at": "2018-03-30T11:25:50.393Z", "key": "eo1RuB6S537cKTxr_d2uLQ", "pano": false, "user_key": "-tUIOh7mZ9oUczk7LaMqFQ", "username": "andreas2"}, "geometry": {"type": "Point", "coordinates": [19.106168629728018, 47.486878303210005]}}, {"type": "Feature", "properties": {"ca": 114.81779324065974, "camera_make": "none", "camera_model": "none", "captured_at": "2018-03-30T11:25:50.225Z", "key": "p-_TrHK-fG8YMepZ3u_JoQ", "pano": false, "user_key": "-tUIOh7mZ9oUczk7LaMqFQ", "username": "andreas2"}, "geometry": {"type": "Point", "coordinates": [19.106144529167977, 47.48688583463502]}}, {"type": "Feature", "properties": {"ca": 114.81779324065974, "camera_make": "none", "camera_model": "none", "captured_at": "2018-03-30T11:25:50.057Z", "key": "VbOvU5s3YksIyV-m8ychpg", "pano": false, "user_key": "-tUIOh7mZ9oUczk7LaMqFQ", "username": "andreas2"}, "geometry": {"type": "Point", "coordinates": [19.106120428607937, 47.48689336606003]}}, {"type": "Feature", "properties": {"ca": 113.70967738357996, "camera_make": "none", "camera_model": "none", "captured_at": "2018-03-30T11:25:49.897Z", "key": "_DzQgvYn1MViHDoPPRKfzQ", "pano": false, "user_key": "-tUIOh7mZ9oUczk7LaMqFQ", "username": "andreas2"}, "geometry": {"type": "Point", "coordinates": [19.106096190464996, 47.48690069186199]}}, {"type": "Feature", "properties": {"ca": 113.70967738357996, "camera_make": "none", "camera_model": "none", "captured_at": "2018-03-30T11:25:49.741Z", "key": "ZZHHAZDw2wCUv4IlDr4xkQ", "pano": false, "user_key": "-tUIOh7mZ9oUczk7LaMqFQ", "username": "andreas2"}, "geometry": {"type": "Point", "coordinates": [19.10607187995504, 47.48690790659401]}}, {"type": "Feature", "properties": {"ca": 113.70967738357996, "camera_make": "none", "camera_model": "none", "captured_at": "2018-03-30T11:25:49.584Z", "key": "5wnEuHrV4dMXvyl6hizJFQ", "pano": false, "user_key": "-tUIOh7mZ9oUczk7LaMqFQ", "username": "andreas2"}, "geometry": {"type": "Point", "coordinates": [19.106047569444968, 47.48691512132598]}}, {"type": "Feature", "properties": {"ca": 113.70967738357996, "camera_make": "none", "camera_model": "none", "captured_at": "2018-03-30T11:25:49.427Z", "key": "kNR5ku965AsXJuX2ljm1MQ", "pano": false, "user_key": "-tUIOh7mZ9oUczk7LaMqFQ", "username": "andreas2"}, "geometry": {"type": "Point", "coordinates": [19.10602325893501, 47.486922336058]}}, {"type": "Feature", "properties": {"ca": 113.70967738357996, "camera_make": "none", "camera_model": "none", "captured_at": "2018-03-30T11:25:49.270Z", "key": "yhdxkdA40m7ojBxklK8VcQ", "pano": false, "user_key": "-tUIOh7mZ9oUczk7LaMqFQ", "username": "andreas2"}, "geometry": {"type": "Point", "coordinates": [19.10599894842494, 47.48692955079002]}}, {"type": "Feature", "properties": {"ca": 113.70967738357996, "camera_make": "none", "camera_model": "none", "captured_at": "2018-03-30T11:25:49.113Z", "key": "w4qdUfqbKyCfIqoTMcKW8A", "pano": false, "user_key": "-tUIOh7mZ9oUczk7LaMqFQ", "username": "andreas2"}, "geometry": {"type": "Point", "coordinates": [19.105974637914983, 47.48693676552199]}}, {"type": "Feature", "properties": {"ca": 112.7918799408962, "camera_make": "none", "camera_model": "none", "captured_at": "2018-03-30T11:25:48.958Z", "key": "PLx8X6Onih0AAyWyoPtJYg", "pano": false, "user_key": "-tUIOh7mZ9oUczk7LaMqFQ", "username": "andreas2"}, "geometry": {"type": "Point", "coordinates": [19.10595028088801, 47.486943907896034]}}, {"type": "Feature", "properties": {"ca": 112.7918799408962, "camera_make": "none", "camera_model": "none", "captured_at": "2018-03-30T11:25:48.807Z", "key": "v5FO54WFx9Eor8GgenYJhQ", "pano": false, "user_key": "-tUIOh7mZ9oUczk7LaMqFQ", "username": "andreas2"}, "geometry": {"type": "Point", "coordinates": [19.10592580333605, 47.486950858312014]}}, {"type": "Feature", "properties": {"ca": 112.7918799408962, "camera_make": "none", "camera_model": "none", "captured_at": "2018-03-30T11:25:48.656Z", "key": "OZdtlu7vx3fT5k78fGjMGw", "pano": false, "user_key": "-tUIOh7mZ9oUczk7LaMqFQ", "username": "andreas2"}, "geometry": {"type": "Point", "coordinates": [19.105901325783975, 47.48695780872799]}}, {"type": "Feature", "properties": {"ca": 18.53131103515625, "camera_make": "samsung", "camera_model": "SM-J320FN", "captured_at": "2018-03-25T12:03:28.560Z", "key": "85VSXsy9H2_2hjJbonkrRg", "pano": false, "user_key": "i1FGvYWQoDeMVAlkvDwvUA", "username": "vst"}, "geometry": {"type": "Point", "coordinates": [19.108009770822264, 47.48668478978777]}}, {"type": "Feature", "properties": {"ca": 21.513946533203125, "camera_make": "samsung", "camera_model": "SM-J320FN", "captured_at": "2018-03-25T12:03:27.201Z", "key": "mERtSJmscz5L_B8EFoG11w", "pano": false, "user_key": "i1FGvYWQoDeMVAlkvDwvUA", "username": "vst"}, "geometry": {"type": "Point", "coordinates": [19.10793358149408, 47.486540433786104]}}, {"type": "Feature", "properties": {"ca": 198.30438232421875, "camera_make": "Apple", "camera_model": "iPhone", "captured_at": "2018-03-09T12:39:30.127Z", "key": "M6UlkUL0WDIkgRETV2zt5A", "pano": false, "user_key": "8TPk6Es4DDJZGBRAJnfcpA", "username": "zsezo"}, "geometry": {"type": "Point", "coordinates": [19.10740859808311, 47.486526109322426]}}, {"type": "Feature", "properties": {"ca": 198.407958984375, "camera_make": "Apple", "camera_model": "iPhone", "captured_at": "2018-03-09T12:39:29.119Z", "key": "pZxtL0WLXj4_eVbFvKQ44w", "pano": false, "user_key": "8TPk6Es4DDJZGBRAJnfcpA", "username": "zsezo"}, "geometry": {"type": "Point", "coordinates": [19.107448747399303, 47.48660812624496]}}, {"type": "Feature", "properties": {"ca": 209.19696044921875, "camera_make": "Apple", "camera_model": "iPhone", "captured_at": "2018-03-09T12:39:28.102Z", "key": "hTrwF0V4izNTvDwmUCr_Kw", "pano": false, "user_key": "8TPk6Es4DDJZGBRAJnfcpA", "username": "zsezo"}, "geometry": {"type": "Point", "coordinates": [19.107485879230353, 47.48668352146399]}}, {"type": "Feature", "properties": {"ca": 200.64556884765625, "camera_make": "Apple", "camera_model": "iPhone", "captured_at": "2018-03-09T12:39:27.127Z", "key": "a6SGNMrOs80KGWT4C181Ag", "pano": false, "user_key": "8TPk6Es4DDJZGBRAJnfcpA", "username": "zsezo"}, "geometry": {"type": "Point", "coordinates": [19.107537344115826, 47.486745757095036]}}, {"type": "Feature", "properties": {"ca": 199.509521484375, "camera_make": "Apple", "camera_model": "iPhone", "captured_at": "2018-03-09T12:39:26.125Z", "key": "wzpiZ1ShHdWminzn1vlUXg", "pano": false, "user_key": "8TPk6Es4DDJZGBRAJnfcpA", "username": "zsezo"}, "geometry": {"type": "Point", "coordinates": [19.107581181469413, 47.486824379346785]}}, {"type": "Feature", "properties": {"ca": 201.498046875, "camera_make": "Apple", "camera_model": "iPhone", "captured_at": "2018-03-09T12:39:25.124Z", "key": "MRG2iAPz6DoAVJGxjCE7jg", "pano": false, "user_key": "8TPk6Es4DDJZGBRAJnfcpA", "username": "zsezo"}, "geometry": {"type": "Point", "coordinates": [19.107616888376924, 47.486892482310054]}}, {"type": "Feature", "properties": {"ca": 195.8402099609375, "camera_make": "Apple", "camera_model": "iPhone", "captured_at": "2018-03-09T12:39:24.123Z", "key": "KajFjFIYhbCfbbPu3BGw4w", "pano": false, "user_key": "8TPk6Es4DDJZGBRAJnfcpA", "username": "zsezo"}, "geometry": {"type": "Point", "coordinates": [19.107651086541864, 47.486951155632255]}}, {"type": "Feature", "properties": {"ca": 203.10235595703125, "camera_make": "Apple", "camera_model": "iPhone", "captured_at": "2018-03-09T12:39:23.121Z", "key": "oqpk_icuYqjGJFy65sWXcA", "pano": false, "user_key": "8TPk6Es4DDJZGBRAJnfcpA", "username": "zsezo"}, "geometry": {"type": "Point", "coordinates": [19.10766986200497, 47.486995873085675]}}]}